{
	"data": {
		"Chorus of Insanity": {
			"1_stack": 19701,
			"2_stack": 20495,
			"3_stack": 21293
		},
		"Spiteful Apparitions": {
			"1_stack": 19536,
			"2_stack": 20147,
			"3_stack": 20759
		},
		"Searing Dialogue": {
			"1_stack": 19213,
			"2_stack": 19517,
			"3_stack": 20869
		},
		"Whispers of the Damned": {
			"1_stack": 19521,
			"2_stack": 19980,
			"3_stack": 20446
		},
		"Death Throes": {
			"1_stack": 19495,
			"2_stack": 20074,
			"3_stack": 20659
		},
		"Thought Harvester": {
			"1_stack": 19412,
			"2_stack": 19654,
			"3_stack": 19901
		},
		"Treacherous Covenant": {
			"1_stack": 19832,
			"2_stack": 20741,
			"3_stack": 21657
		},
		"Blightborne Infusion": {
			"1_stack": 19775,
			"2_stack": 20639,
			"3_stack": 21497
		},
		"Swirling Sands": {
			"1_stack": 19687,
			"2_stack": 20455,
			"3_stack": 21221
		},
		"Dagger in the Back Behind": {
			"1_stack": 19662,
			"2_stack": 20398,
			"3_stack": 21138
		},
		"Endless Hunger": {
			"1_stack": 19588,
			"2_stack": 20259,
			"3_stack": 20929
		},
		"Ancients Bulwark": {
			"1_stack": 19592,
			"2_stack": 20263,
			"3_stack": 20928
		},
		"Rezans Fury": {
			"1_stack": 19560,
			"2_stack": 20201,
			"3_stack": 20840
		},
		"Relational Normalization Gizmo": {
			"1_stack": 19588,
			"2_stack": 20200,
			"3_stack": 20821
		},
		"Meticulous Scheming": {
			"1_stack": 19558,
			"2_stack": 20182,
			"3_stack": 20779
		},
		"Battlefield Focus": {
			"1_stack": 19525,
			"2_stack": 20135,
			"3_stack": 20745
		},
		"Unstable Catalyst": {
			"1_stack": 19531,
			"2_stack": 20136,
			"3_stack": 20740
		},
		"Archive of the Titans": {
			"1_stack": 19521,
			"2_stack": 20124,
			"3_stack": 20726
		},
		"Laser Matrix": {
			"1_stack": 19489,
			"2_stack": 20063,
			"3_stack": 20628
		},
		"Tidal Surge": {
			"1_stack": 19491,
			"2_stack": 20062,
			"3_stack": 20627
		},
		"Filthy Transfusion": {
			"1_stack": 19489,
			"2_stack": 20057,
			"3_stack": 20626
		},
		"Thunderous Blast": {
			"1_stack": 19469,
			"2_stack": 20014,
			"3_stack": 20564
		},
		"Secrets of the Deep": {
			"1_stack": 19465,
			"2_stack": 20007,
			"3_stack": 20551
		},
		"Tradewinds": {
			"1_stack": 19453,
			"2_stack": 19985,
			"3_stack": 20511
		},
		"Sylvanas Resolve": {
			"1_stack": 19444,
			"2_stack": 19961,
			"3_stack": 20493
		},
		"Glory in Battle": {
			"1_stack": 19429,
			"2_stack": 19955,
			"3_stack": 20490
		},
		"Apothecarys Concoctions": {
			"1_stack": 19442,
			"2_stack": 19967,
			"3_stack": 20489
		},
		"Blood Rite": {
			"1_stack": 19443,
			"2_stack": 19954,
			"3_stack": 20451
		},
		"Overwhelming Power": {
			"1_stack": 19439,
			"2_stack": 19945,
			"3_stack": 20450
		},
		"Whispers of the Damned Chorus of Insanity combo": {
			"1_stack": 0,
			"2_stack": 20444,
			"3_stack": 0
		},
		"Dagger in the Back Front": {
			"1_stack": 19430,
			"2_stack": 19934,
			"3_stack": 20443
		},
		"Spiteful Apparitions Chorus of Insanity combo": {
			"1_stack": 0,
			"2_stack": 20442,
			"3_stack": 0
		},
		"Shadow of Elune": {
			"1_stack": 19430,
			"2_stack": 19930,
			"3_stack": 20411
		},
		"Seductive Power": {
			"1_stack": 19418,
			"2_stack": 19913,
			"3_stack": 20409
		},
		"Incite the Pack": {
			"1_stack": 19413,
			"2_stack": 19904,
			"3_stack": 20396
		},
		"Barrage Of Many Bombs": {
			"1_stack": 19409,
			"2_stack": 19904,
			"3_stack": 20396
		},
		"Death Throes Chorus of Insanity combo": {
			"1_stack": 0,
			"2_stack": 20296,
			"3_stack": 0
		},
		"Thought Harvester Chorus of Insanity combo": {
			"1_stack": 0,
			"2_stack": 20208,
			"3_stack": 0
		},
		"Thought Harvester Searing Dialogue combo": {
			"1_stack": 0,
			"2_stack": 20198,
			"3_stack": 0
		},
		"Whispers of the Damned Spiteful Apparitions combo": {
			"1_stack": 0,
			"2_stack": 20138,
			"3_stack": 0
		},
		"Death Throes Spiteful Apparitions combo": {
			"1_stack": 0,
			"2_stack": 20111,
			"3_stack": 0
		},
		"Death Throes Whispers of the Damned combo": {
			"1_stack": 0,
			"2_stack": 20100,
			"3_stack": 0
		},
		"Synaptic Spark Capacitor": {
			"1_stack": 19287,
			"2_stack": 19660,
			"3_stack": 20037
		},
		"Thought Harvester Spiteful Apparitions combo": {
			"1_stack": 0,
			"2_stack": 20022,
			"3_stack": 0
		},
		"Whispers of the Damned Thought Harvester combo": {
			"1_stack": 0,
			"2_stack": 20014,
			"3_stack": 0
		},
		"Searing Dialogue Chorus of Insanity combo": {
			"1_stack": 0,
			"2_stack": 20007,
			"3_stack": 0
		},
		"Death Throes Thought Harvester combo": {
			"1_stack": 0,
			"2_stack": 19987,
			"3_stack": 0
		},
		"Ruinous Bolt": {
			"1_stack": 19259,
			"2_stack": 19599,
			"3_stack": 19941
		},
		"Gutripper": {
			"1_stack": 19234,
			"2_stack": 19545,
			"3_stack": 19858
		},
		"Whispers of the Damned Searing Dialogue combo": {
			"1_stack": 0,
			"2_stack": 19834,
			"3_stack": 0
		},
		"Searing Dialogue Spiteful Apparitions combo": {
			"1_stack": 0,
			"2_stack": 19829,
			"3_stack": 0
		},
		"Unstable Flames": {
			"1_stack": 19216,
			"2_stack": 19513,
			"3_stack": 19812
		},
		"Ricocheting Inflatable Pyrosaw": {
			"1_stack": 19219,
			"2_stack": 19512,
			"3_stack": 19803
		},
		"Heed My Call": {
			"1_stack": 19212,
			"2_stack": 19501,
			"3_stack": 19796
		},
		"Death Throes Searing Dialogue combo": {
			"1_stack": 0,
			"2_stack": 19790,
			"3_stack": 0
		},
		"Retaliatory Fury": {
			"1_stack": 19202,
			"2_stack": 19490,
			"3_stack": 19769
		},
		"Champion of Azeroth": {
			"1_stack": 19744,
			"2_stack": 0,
			"3_stack": 0
		},
		"Bonded Souls": {
			"1_stack": 19194,
			"2_stack": 19466,
			"3_stack": 19734
		},
		"Elemental Whirl": {
			"1_stack": 19172,
			"2_stack": 19425,
			"3_stack": 19676
		},
		"Azerite Globules": {
			"1_stack": 19143,
			"2_stack": 19363,
			"3_stack": 19584
		},
		"Collective Will": {
			"1_stack": 19127,
			"2_stack": 19327,
			"3_stack": 19532
		},
		"Blood Siphon": {
			"1_stack": 19116,
			"2_stack": 19315,
			"3_stack": 19511
		},
		"On My Way": {
			"1_stack": 19113,
			"2_stack": 19308,
			"3_stack": 19503
		},
		"Earthlink": {
			"1_stack": 19099,
			"2_stack": 19282,
			"3_stack": 19462
		},
		"Combined Might": {
			"1_stack": 19070,
			"2_stack": 19216,
			"3_stack": 19367
		},
		"Azerite Empowered": {
			"1_stack": 19006,
			"2_stack": 19062,
			"3_stack": 19142
		},
		"Fight or Flight": {
			"1_stack": 18923,
			"2_stack": 18923,
			"3_stack": 18921
		},
		"Base": {
			"1_stack": 18920,
			"2_stack": 0,
			"3_stack": 0
		}
	},
	"Data_type": "traits",
	"spell_ids" : {
		"Ancients Bulwark ":"287631",
		"Apothecarys Concoctions ":"287604",
		"Archive of the Titans ":"280708",
		"Azerite Empowered ":"263978",
		"Azerite Globules ":"279955",
		"Barrage Of Many Bombs ":"280163",
		"Battlefield Focus ":"280582",
		"Blightborne Infusion ":"273823",
		"Blood Rite ":"280409",
		"Blood Siphon ":"264108",
		"Champion of Azeroth ":"270583",
		"Chorus of Insanity ":"278661",
		"Collective Will ":"280837",
		"Combined Might ":"280848",
		"Dagger in the Back Behind ":"280285",
		"Dagger in the Back Front ":"280285",
		"Death Throes ":"278659",
		"Earthlink ":"279927",
		"Elemental Whirl ":"270667",
		"Endless Hunger ":"287662",
		"Fight or Flight ":"287818",
		"Filthy Transfusion ":"273836",
		"Glory in Battle ":"280852",
		"Gutripper ":"266937",
		"Heed My Call ":"271681",
		"Incite the Pack ":"280410",
		"Laser Matrix ":"280702",
		"Lifespeed":"267665",
		"Meticulous Scheming ":"273684",
		"On My Way ":"267879",
		"Overwhelming Power ":"266180",
		"Relational Normalization Gizmo ":"280178",
		"Retaliatory Fury ":"280785",
		"Rezans Fury ":"281834",
		"Ricocheting Inflatable Pyrosaw ":"280168",
		"Ruinous Bolt ":"280206",
		"Searing Dialogue ":"272788",
		"Secrets of the Deep ":"273829",
		"Shadow of Elune ": "287471" ,
		"Spiteful Apparitions ":"277682",
		"Swirling Sands ":"280433",
		"Sylvanas Resolve ":"280810",
		"Synaptic Spark Capacitor ":"280174",
		"Thought Harvester ":"273320",
		"Thunderous Blast ":"280384",
		"Tidal Surge ":"280404",
		"Tradewinds ":"281843",
		"Unstable Catalyst ":"281516",
		"Unstable Flames ":"279902",
		"Whispers of the Damned ":"275726"
	},
	"simulated_steps": [
		"1_stack",
		"2_stack",
		"3_stack"
	],
	"sorted_data_keys": [
		"Treacherous Covenant ",
		"Blightborne Infusion ",
		"Death Throes Whispers of the Damned combo ",
		"Chorus of Insanity ",
		"Swirling Sands ",
		"Dagger in the Back Behind ",
		"Ancients Bulwark ",
		"Relational Normalization Gizmo ",
		"Endless Hunger ",
		"Rezans Fury ",
		"Meticulous Scheming ",
		"Spiteful Apparitions ",
		"Unstable Catalyst ",
		"Battlefield Focus ",
		"Whispers of the Damned ",
		"Archive of the Titans ",
		"Death Throes ",
		"Tidal Surge ",
		"Laser Matrix ",
		"Filthy Transfusion ",
		"Thunderous Blast ",
		"Secrets of the Deep ",
		"Tradewinds ",
		"Sylvanas Resolve ",
		"Blood Rite ",
		"Apothecarys Concoctions ",
		"Overwhelming Power ",
		"Whispers of the Damned Chorus of Insanity combo ",
		"Dagger in the Back Front ",
		"Glory in Battle ",
		"Spiteful Apparitions Chorus of Insanity combo ",
		"Shadow of Elune ",
		"Thought Harvester ",
		"Seductive Power ",
		"Incite the Pack ",
		"Barrage Of Many Bombs ",
		"Death Throes Chorus of Insanity combo ",
		"Thought Harvester Searing Dialogue combo ",
		"Thought Harvester Chorus of Insanity combo ",
		"Searing Dialogue ",
		"Whispers of the Damned Spiteful Apparitions combo ",
		"Death Throes Spiteful Apparitions combo ",
		"Synaptic Spark Capacitor ",
		"Thought Harvester Spiteful Apparitions combo ",
		"Whispers of the Damned Thought Harvester combo ",
		"Searing Dialogue Chorus of Insanity combo ",
		"Death Throes Thought Harvester combo ",
		"Ruinous Bolt ",
		"Gutripper ",
		"Whispers of the Damned Searing Dialogue combo ",
		"Searing Dialogue Spiteful Apparitions combo ",
		"Unstable Flames "
	]
}