{
	"data": {
		"Searing Dialogue 3 Chorus of Insanity 2 Thought Harvester 1": {
			"1_stack": 69534
		},
		"Chorus of Insanity 3 Spiteful Apparitions 2 Whispers of the Damned 1": {
			"1_stack": 68970
		},
		"Searing Dialogue 3 Chorus of Insanity 1 Thought Harvester 1 Whispers of the Damned 1": {
			"1_stack": 68641
		},
		"Searing Dialogue 3 Chorus of Insanity 3": {
			"1_stack": 68561
		},
		"Whispers of the Damned 3 Chorus of Insanity 3": {
			"1_stack": 68190
		},
		"Searing Dialogue 3 Chorus of Insanity 1 Thought Harvester 1 Spiteful Apparitions 1": {
			"1_stack": 68121
		},
		"Searing Dialogue 3 Death Throes 1 Thought Harvester 1 Barrage of Many Bombs 1": {
			"1_stack": 67829
		},
		"Chorus of Insanity 3 Heart of Darkness 1 Spiteful Apparitions 1 Whispers of the Damned 1": {
			"1_stack": 67518
		},
		"Death Throes 3 Chorus of Insanity 3": {
			"1_stack": 67509
		},
		"Searing Dialogue 3 Death Throes 2 Thought Harvester 1": {
			"1_stack": 67358
		},
		"Spiteful Apparitions 3 Chorus of Insanity 3": {
			"1_stack": 66983
		},
		"Spiteful Apparitions 3 Chorus of Insanity 2 Whispers of the Damned 1": {
			"1_stack": 66856
		},
		"Searing Dialogue 3 Spiteful Apparitions 1 Thought Harvester 1 Whispers of the Damned 1": {
			"1_stack": 66681
		},
		"Thought Harvester 3 Chorus of Insanity 3": {
			"1_stack": 66180
		},
		"Chorus of Insanity 3 Heart of Darkness 2 Whispers of the Damned 1": {
			"1_stack": 66113
		},
		"Death Throes 3 Searing Dialogue 3": {
			"1_stack": 66090
		},
		"Spiteful Apparitions 3 Searing Dialogue 1 Thought Harvester 1 Chorus of Insanity 1": {
			"1_stack": 64953
		},
		"Thought Harvester 3 Searing Dialogue 3": {
			"1_stack": 64592
		},
		"Spiteful Apparitions 3 Searing Dialogue 2 Thought Harvester 1": {
			"1_stack": 64534
		},
		"Searing Dialogue 3 Spiteful Apparitions 3": {
			"1_stack": 64004
		},
		"Whispers of the Damned 3 Searing Dialogue 3": {
			"1_stack": 63834
		},
		"Whispers of the Damned 1 Chorus of Insanity 2": {
			"1_stack": 62999
		},
		"Death Throes 3 Whispers of the Damned 3": {
			"1_stack": 62957
		},
		"Chorus of Insanity 3 Heart of Darkness 3": {
			"1_stack": 62826
		},
		"Thought Harvester 1 Chorus of Insanity 2": {
			"1_stack": 62618
		},
		"Whispers of the Damned 3 Thought Harvester 3": {
			"1_stack": 62474
		},
		"Death Throes 3 Spiteful Apparitions 3": {
			"1_stack": 62459
		},
		"Searing Dialogue 1 Chorus of Insanity 2": {
			"1_stack": 62002
		},
		"Whispers of the Damned 3 Spiteful Apparitions 3": {
			"1_stack": 61978
		},
		"Death Throes 3 Thought Harvester 3": {
			"1_stack": 61883
		},
		"Death Throes 1 Chorus of Insanity 2": {
			"1_stack": 61791
		},
		"Spiteful Apparitions 1 Chorus of Insanity 2": {
			"1_stack": 61608
		},
		"Thought Harvester 1 Searing Dialogue 2": {
			"1_stack": 61598
		},
		"Thought Harvester 3 Spiteful Apparitions 3": {
			"1_stack": 61425
		},
		"Chorus of Insanity 1 Searing Dialogue 2": {
			"1_stack": 61097
		},
		"Chorus of Insanity 1 Whispers of the Damned 2": {
			"1_stack": 60905
		},
		"Chorus of Insanity 1 Thought Harvester 2": {
			"1_stack": 60682
		},
		"Chorus of Insanity 1 Death Throes 2": {
			"1_stack": 60669
		},
		"Thought Harvester 1 Whispers of the Damned 2": {
			"1_stack": 60401
		},
		"Whispers of the Damned 1 Searing Dialogue 2": {
			"1_stack": 60310
		},
		"Death Throes 1 Searing Dialogue 2": {
			"1_stack": 60283
		},
		"Thought Harvester Chorus of Insanity": {
			"1_stack": 60189
		},
		"Chorus of Insanity 1 Spiteful Apparitions 2": {
			"1_stack": 60082
		},
		"Searing Dialogue 1 Death Throes 2": {
			"1_stack": 60056
		},
		"Whispers of the Damned 1 Thought Harvester 2": {
			"1_stack": 60011
		},
		"Whispers of the Damned Chorus of Insanity": {
			"1_stack": 60009
		},
		"Thought Harvester 1 Death Throes 2": {
			"1_stack": 59928
		},
		"Whispers of the Damned 1 Death Throes 2": {
			"1_stack": 59891
		},
		"Searing Dialogue 1 Thought Harvester 2": {
			"1_stack": 59844
		},
		"Spiteful Apparitions 1 Searing Dialogue 2": {
			"1_stack": 59707
		},
		"Thought Harvester 1 Spiteful Apparitions 2": {
			"1_stack": 59559
		},
		"Whispers of the Damned Thought Harvester": {
			"1_stack": 59482
		},
		"Searing Dialogue Chorus of Insanity": {
			"1_stack": 59467
		},
		"Searing Dialogue 1 Whispers of the Damned 2": {
			"1_stack": 59455
		},
		"Thought Harvester Searing Dialogue": {
			"1_stack": 59355
		},
		"Death Throes 1 Thought Harvester 2": {
			"1_stack": 59309
		},
		"Death Throes 1 Whispers of the Damned 2": {
			"1_stack": 59267
		},
		"Death Throes Chorus of Insanity": {
			"1_stack": 59228
		},
		"Spiteful Apparitions 1 Thought Harvester 2": {
			"1_stack": 59174
		},
		"Spiteful Apparitions 1 Death Throes 2": {
			"1_stack": 59108
		},
		"Whispers of the Damned 1 Spiteful Apparitions 2": {
			"1_stack": 59084
		},
		"Whispers of the Damned 3 Heart of Darkness 3": {
			"1_stack": 59023
		},
		"Spiteful Apparitions 1 Whispers of the Damned 2": {
			"1_stack": 58969
		},
		"Spiteful Apparitions Chorus of Insanity": {
			"1_stack": 58964
		},
		"Searing Dialogue 1 Spiteful Apparitions 2": {
			"1_stack": 58945
		},
		"Death Throes Thought Harvester": {
			"1_stack": 58827
		},
		"Thought Harvester Spiteful Apparitions": {
			"1_stack": 58684
		},
		"Death Throes 1 Spiteful Apparitions 2": {
			"1_stack": 58675
		},
		"Death Throes Searing Dialogue": {
			"1_stack": 58544
		},
		"Whispers of the Damned Searing Dialogue": {
			"1_stack": 58494
		},
		"Death Throes Whispers of the Damned": {
			"1_stack": 58468
		},
		"Spiteful Apparitions 3 Heart of Darkness 3": {
			"1_stack": 58335
		},
		"Whispers of the Damned Spiteful Apparitions": {
			"1_stack": 58147
		},
		"Searing Dialogue Spiteful Apparitions": {
			"1_stack": 58028
		},
		"Death Throes Spiteful Apparitions": {
			"1_stack": 57729
		},
		"Base": {
			"1_stack": 55528,
		}
	},
	"sorted_data_keys": [
		"Searing Dialogue 3 Chorus of Insanity 2 Thought Harvester 1",
		"Chorus of Insanity 3 Spiteful Apparitions 2 Whispers of the Damned 1",
		"Searing Dialogue 3 Chorus of Insanity 1 Thought Harvester 1 Whispers of the Damned 1",
		"Searing Dialogue 3 Chorus of Insanity 3",
		"Whispers of the Damned 3 Chorus of Insanity 3",
		"Searing Dialogue 3 Chorus of Insanity 1 Thought Harvester 1 Spiteful Apparitions 1",
		"Searing Dialogue 3 Death Throes 1 Thought Harvester 1 Barrage of Many Bombs 1",
		"Chorus of Insanity 3 Heart of Darkness 1 Spiteful Apparitions 1 Whispers of the Damned 1",
		"Death Throes 3 Chorus of Insanity 3",
		"Searing Dialogue 3 Death Throes 2 Thought Harvester 1",
		"Spiteful Apparitions 3 Chorus of Insanity 3",
		"Spiteful Apparitions 3 Chorus of Insanity 2 Whispers of the Damned 1",
		"Searing Dialogue 3 Spiteful Apparitions 1 Thought Harvester 1 Whispers of the Damned 1",
		"Thought Harvester 3 Chorus of Insanity 3",
		"Chorus of Insanity 3 Heart of Darkness 2 Whispers of the Damned 1",
		"Death Throes 3 Searing Dialogue 3",
		"Spiteful Apparitions 3 Searing Dialogue 1 Thought Harvester 1 Chorus of Insanity 1",
		"Thought Harvester 3 Searing Dialogue 3",
		"Spiteful Apparitions 3 Searing Dialogue 2 Thought Harvester 1",
		"Searing Dialogue 3 Spiteful Apparitions 3",
		"Whispers of the Damned 3 Searing Dialogue 3",
		"Whispers of the Damned 1 Chorus of Insanity 2",
		"Death Throes 3 Whispers of the Damned 3",
		"Chorus of Insanity 3 Heart of Darkness 3",
		"Thought Harvester 1 Chorus of Insanity 2",
		"Whispers of the Damned 3 Thought Harvester 3",
		"Death Throes 3 Spiteful Apparitions 3",
		"Searing Dialogue 1 Chorus of Insanity 2",
		"Whispers of the Damned 3 Spiteful Apparitions 3",
		"Death Throes 3 Thought Harvester 3",
		"Death Throes 1 Chorus of Insanity 2",
		"Spiteful Apparitions 1 Chorus of Insanity 2",
		"Thought Harvester 1 Searing Dialogue 2",
		"Thought Harvester 3 Spiteful Apparitions 3",
		"Chorus of Insanity 1 Searing Dialogue 2",
		"Chorus of Insanity 1 Whispers of the Damned 2",
		"Chorus of Insanity 1 Thought Harvester 2",
		"Chorus of Insanity 1 Death Throes 2",
		"Thought Harvester 1 Whispers of the Damned 2",
		"Whispers of the Damned 1 Searing Dialogue 2",
		"Death Throes 1 Searing Dialogue 2",
		"Thought Harvester Chorus of Insanity",
		"Chorus of Insanity 1 Spiteful Apparitions 2",
		"Searing Dialogue 1 Death Throes 2",
		"Whispers of the Damned 1 Thought Harvester 2",
		"Whispers of the Damned Chorus of Insanity",
		"Thought Harvester 1 Death Throes 2",
		"Whispers of the Damned 1 Death Throes 2",
		"Searing Dialogue 1 Thought Harvester 2",
		"Spiteful Apparitions 1 Searing Dialogue 2",
		"Thought Harvester 1 Spiteful Apparitions 2",
		"Whispers of the Damned Thought Harvester",
		"Searing Dialogue Chorus of Insanity",
		"Searing Dialogue 1 Whispers of the Damned 2",
		"Thought Harvester Searing Dialogue",
		"Death Throes 1 Thought Harvester 2",
		"Death Throes 1 Whispers of the Damned 2",
		"Death Throes Chorus of Insanity",
		"Spiteful Apparitions 1 Thought Harvester 2",
		"Spiteful Apparitions 1 Death Throes 2",
		"Whispers of the Damned 1 Spiteful Apparitions 2",
		"Whispers of the Damned 3 Heart of Darkness 3",
		"Spiteful Apparitions 1 Whispers of the Damned 2",
		"Spiteful Apparitions Chorus of Insanity",
		"Searing Dialogue 1 Spiteful Apparitions 2",
		"Death Throes Thought Harvester",
		"Thought Harvester Spiteful Apparitions",
		"Death Throes 1 Spiteful Apparitions 2",
		"Death Throes Searing Dialogue",
		"Whispers of the Damned Searing Dialogue",
		"Death Throes Whispers of the Damned",
		"Spiteful Apparitions 3 Heart of Darkness 3",
		"Whispers of the Damned Spiteful Apparitions",
		"Searing Dialogue Spiteful Apparitions",
		"Death Throes Spiteful Apparitions"
	]
}