{
	"data": {
		"Chorus of Insanity": {
			"1_stack": 13628,
			"2_stack": 14294,
			"3_stack": 14957
		},
		"Blightborne Infusion": {
			"1_stack": 13458,
			"2_stack": 13948,
			"3_stack": 14444
		},
		"Champion of Azeroth": {
			"1_stack": 13433,
			"2_stack": 13892,
			"3_stack": 14392
		},
		"Dagger in the Back Behind": {
			"1_stack": 13475,
			"2_stack": 13976,
			"3_stack": 14481
		},
		"Swirling Sands": {
			"1_stack": 13411,
			"2_stack": 13842,
			"3_stack": 14289
		},
		"Spiteful Apparitions": {
			"1_stack": 13377,
			"2_stack": 13784,
			"3_stack": 14183
		},
		"Rezans Fury": {
			"1_stack": 13411,
			"2_stack": 13851,
			"3_stack": 14293
		},
		"Tidal Surge": {
			"1_stack": 13408,
			"2_stack": 13849,
			"3_stack": 14289
		},
		"Synaptic Spark Capacitor": {
			"1_stack": 13321,
			"2_stack": 13674,
			"3_stack": 14024
		},
		"Whispers of the Damned": {
			"1_stack": 13375,
			"2_stack": 13783,
			"3_stack": 14189
		},
		"Archive of the Titans": {
			"1_stack": 13357,
			"2_stack": 13746,
			"3_stack": 14129
		},
		"Unstable Catalyst": {
			"1_stack": 13341,
			"2_stack": 13715,
			"3_stack": 14088
		},
		"Relational Normalization Gizmo": {
			"1_stack": 13357,
			"2_stack": 13735,
			"3_stack": 14090
		},
		"Laser Matrix": {
			"1_stack": 13364,
			"2_stack": 13747,
			"3_stack": 14138
		},
		"Battlefield Focus": {
			"1_stack": 13415,
			"2_stack": 13867,
			"3_stack": 14307
		},
		"Death Throes": {
			"1_stack": 13294,
			"2_stack": 13612,
			"3_stack": 13935
		},
		"Filthy Transfusion": {
			"1_stack": 13348,
			"2_stack": 13727,
			"3_stack": 14105
		},
		"Thunderous Blast": {
			"1_stack": 13345,
			"2_stack": 13706,
			"3_stack": 14076
		},
		"Meticulous Scheming": {
			"1_stack": 13339,
			"2_stack": 13687,
			"3_stack": 14021
		},
		"Secrets of the Deep": {
			"1_stack": 13298,
			"2_stack": 13635,
			"3_stack": 13969
		},
		"Barrage Of Many Bombs": {
			"1_stack": 13256,
			"2_stack": 13530,
			"3_stack": 13812
		},
		"Dagger in the Back Front": {
			"1_stack": 13322,
			"2_stack": 13674,
			"3_stack": 14024
		},
		"Sylvanas Resolve": {
			"1_stack": 13292,
			"2_stack": 13614,
			"3_stack": 13933
		},
		"Tradewinds": {
			"1_stack": 13277,
			"2_stack": 13587,
			"3_stack": 13895
		},
		"Glory in Battle": {
			"1_stack": 13243,
			"2_stack": 13534,
			"3_stack": 13852
		},
		"Incite the Pack": {
			"1_stack": 13252,
			"2_stack": 13542,
			"3_stack": 13824
		},
		"Blood Rite": {
			"1_stack": 13274,
			"2_stack": 13557,
			"3_stack": 13836
		},
		"Overwhelming Power": {
			"1_stack": 13221,
			"2_stack": 13506,
			"3_stack": 13771
		},
		"Ruinous Bolt": {
			"1_stack": 13235,
			"2_stack": 13497,
			"3_stack": 13756
		},
		"Ricocheting Inflatable Pyrosaw": {
			"1_stack": 13144,
			"2_stack": 13306,
			"3_stack": 13483
		},
		"Heed My Call": {
			"1_stack": 13162,
			"2_stack": 13354,
			"3_stack": 13547
		},
		"Unstable Flames": {
			"1_stack": 13143,
			"2_stack": 13314,
			"3_stack": 13481
		},
		"Gutripper": {
			"1_stack": 13146,
			"2_stack": 13322,
			"3_stack": 13502
		},
		"Retaliatory Fury": {
			"1_stack": 13135,
			"2_stack": 13296,
			"3_stack": 13462
		},
		"Thought Harvester": {
			"1_stack": 13123,
			"2_stack": 13272,
			"3_stack": 13425
		},
		"Elemental Whirl": {
			"1_stack": 13116,
			"2_stack": 13257,
			"3_stack": 13415
		},
		"Azerite Globules": {
			"1_stack": 13100,
			"2_stack": 13230,
			"3_stack": 13359
		},
		"Earthlink": {
			"1_stack": 13109,
			"2_stack": 13240,
			"3_stack": 13375
		},
		"On My Way": {
			"1_stack": 13091,
			"2_stack": 13209,
			"3_stack": 13329
		},
		"Blood Siphon": {
			"1_stack": 13081,
			"2_stack": 13202,
			"3_stack": 13313
		},
		"Collective Will": {
			"1_stack": 13078,
			"2_stack": 13190,
			"3_stack": 13305
		},
		"Azerite Empowered": {
			"1_stack": 13076,
			"2_stack": 13155,
			"3_stack": 13253
		},
		"Combined Might": {
			"1_stack": 13053,
			"2_stack": 13123,
			"3_stack": 13204
		},
		"Searing Dialogue": {
			"1_stack": 12972,
			"2_stack": 12973,
			"3_stack": 12974
		},
		"Base": {
			"1_stack": 12971,
			"2_stack": 0,
			"3_stack": 0
		}
	},
	"Data_type": "traits",
	"spell_ids" : {
		"Archive of the Titans ":"280708",
		"Azerite Globules ":"279955",
		"Barrage Of Many Bombs ":"280163",
		"Battlefield Focus ":"280582",
		"Blightborne Infusion ":"273823",
		"Blood Rite ":"280409",
		"Blood Siphon ":"264108",
		"Champion of Azeroth ":"270583",
		"Chorus of Insanity ":"278661",
		"Collective Will ":"280837",
		"Combined Might ":"280848",
		"Dagger in the Back Behind ":"280285",
		"Dagger in the Back Front ":"280285",
		"Death Throes ":"278659",
		"Earthlink ":"279927",
		"Elemental Whirl ":"270667",
		"Filthy Transfusion ":"273836",
		"Glory in Battle ":"280852",
		"Gutripper ":"266937",
		"Heed My Call ":"271681",
		"Incite the Pack ":"280410",
		"Laser Matrix ":"280702",
		"Lifespeed":"267665",
		"Meticulous Scheming ":"273684",
		"On My Way ":"267879",
		"Overwhelming Power ":"266180",
		"Relational Normalization Gizmo ":"280178",
		"Retaliatory Fury ":"280785",
		"Rezans Fury ":"281834",
		"Ricocheting Inflatable Pyrosaw ":"280168",
		"Ruinous Bolt ":"280206",
		"Searing Dialogue ":"272788",
		"Secrets of the Deep ":"273829",
		"Spiteful Apparitions ":"277682",
		"Swirling Sands ":"280433",
		"Sylvanas Resolve ":"280810",
		"Synaptic Spark Capacitor ":"280174",
		"Thought Harvester ":"273320",
		"Thunderous Blast ":"280384",
		"Tidal Surge ":"280404",
		"Tradewinds ":"281843",
		"Unstable Catalyst ":"281516",
		"Unstable Flames ":"279902",
		"Whispers of the Damned ":"275726"
	},
	"simulated_steps": [
		"1_stack",
		"2_stack",
		"3_stack"
	],
	"sorted_data_keys": [
		"Chorus of Insanity ",
		"Dagger in the Back Behind ",
		"Blightborne Infusion ",
		"Champion of Azeroth ",
		"Battlefield Focus ",
		"Swirling Sands ",
		"Rezans Fury ",
		"Tidal Surge ",
		"Spiteful Apparitions ",
		"Whispers of the Damned ",
		"Laser Matrix ",
		"Relational Normalization Gizmo ",
		"Archive of the Titans ",
		"Filthy Transfusion ",
		"Thunderous Blast ",
		"Unstable Catalyst ",
		"Meticulous Scheming ",
		"Dagger in the Back Front ",
		"Synaptic Spark Capacitor ",
		"Secrets of the Deep ",
		"Death Throes ",
		"Sylvanas Resolve ",
		"Tradewinds ",
		"Blood Rite ",
		"Barrage Of Many Bombs ",
		"Incite the Pack ",
		"Glory in Battle ",
		"Ruinous Bolt ",
		"Overwhelming Power ",
		"Heed My Call ",
		"Gutripper ",
		"Ricocheting Inflatable Pyrosaw ",
		"Unstable Flames ",
		"Retaliatory Fury ",
		"Thought Harvester ",
		"Elemental Whirl ",
		"Earthlink ",
		"Azerite Globules ",
		"On My Way ",
		"Blood Siphon ",
		"Collective Will ",
		"Azerite Empowered ",
		"Combined Might "
	]
}