{
	"data": {
		"Ancients Bulwark": {
			"1_stack": 41539,
			"2_stack": 43084,
			"3_stack": 44642
		},
		"Apothecarys Concoctions": {
			"1_stack": 40676,
			"2_stack": 41411,
			"3_stack": 42119
		},
		"Arcane Heart": {
			"1_stack": 40685,
			"2_stack": 41320,
			"3_stack": 41928
		},
		"Barrage Of Many Bombs": {
			"1_stack": 41326,
			"2_stack": 42677,
			"3_stack": 43993
		},
		"Battlefield Focus": {
			"1_stack": 40532,
			"2_stack": 41125,
			"3_stack": 41702
		},
		"Blightborne Infusion": {
			"1_stack": 41594,
			"2_stack": 43282,
			"3_stack": 44876
		},
		"Blood Rite": {
			"1_stack": 41119,
			"2_stack": 42275,
			"3_stack": 43306
		},
		"Bonded Souls": {
			"1_stack": 40468,
			"2_stack": 40982,
			"3_stack": 41423
		},
		"Champion of Azeroth": {
			"1_stack": 41444,
			"2_stack": 0,
			"3_stack": 0
		},
		"Chorus of Insanity": {
			"1_stack": 41939,
			"2_stack": 43965,
			"3_stack": 45985
		},
		"Clockwork Heart": {
			"1_stack": 41054,
			"2_stack": 42313,
			"3_stack": 43670
		},
		"Collective Will": {
			"1_stack": 40330,
			"2_stack": 40684,
			"3_stack": 41025
		},
		"Combined Might": {
			"1_stack": 40300,
			"2_stack": 40587,
			"3_stack": 40884
		},
		"Dagger in the Back Behind": {
			"1_stack": 40740,
			"2_stack": 41587,
			"3_stack": 42410
		},
		"Dagger in the Back Front": {
			"1_stack": 40464,
			"2_stack": 40949,
			"3_stack": 41485
		},
		"Death Throes": {
			"1_stack": 40774,
			"2_stack": 41647,
			"3_stack": 42538
		},
		"Fight or Flight": {
			"1_stack": 40488,
			"2_stack": 41030,
			"3_stack": 41573
		},
		"Filthy Transfusion": {
			"1_stack": 40712,
			"2_stack": 41455,
			"3_stack": 42206
		},
		"Glory in Battle": {
			"1_stack": 40880,
			"2_stack": 41850,
			"3_stack": 42801
		},
		"Incite the Pack": {
			"1_stack": 40852,
			"2_stack": 41707,
			"3_stack": 42642
		},
		"Meticulous Scheming": {
			"1_stack": 41007,
			"2_stack": 41976,
			"3_stack": 42876
		},
		"Relational Normalization Gizmo": {
			"1_stack": 41012,
			"2_stack": 42015,
			"3_stack": 42796
		},
		"Retaliatory Fury": {
			"1_stack": 40480,
			"2_stack": 40970,
			"3_stack": 41472
		},
		"Rezans Fury": {
			"1_stack": 40847,
			"2_stack": 41673,
			"3_stack": 42566
		},
		"Ricocheting Inflatable Pyrosaw": {
			"1_stack": 40688,
			"2_stack": 41458,
			"3_stack": 42238
		},
		"Ruinous Bolt": {
			"1_stack": 40365,
			"2_stack": 40780,
			"3_stack": 41305
		},
		"Searing Dialogue": {
			"1_stack": 40899,
			"2_stack": 41838,
			"3_stack": 43179
		},
		"Secrets of the Deep": {
			"1_stack": 40836,
			"2_stack": 41706,
			"3_stack": 42570
		},
		"Seductive Power": {
			"1_stack": 40846,
			"2_stack": 41804,
			"3_stack": 42698
		},
		"Shadow of Elune": {
			"1_stack": 40815,
			"2_stack": 41634,
			"3_stack": 42352
		},
		"Spiteful Apparitions": {
			"1_stack": 40775,
			"2_stack": 41705,
			"3_stack": 42569
		},
		"Swirling Sands": {
			"1_stack": 41413,
			"2_stack": 42879,
			"3_stack": 44397
		},
		"Sylvanas Resolve": {
			"1_stack": 40813,
			"2_stack": 41622,
			"3_stack": 42461
		},
		"Synaptic Spark Capacitor": {
			"1_stack": 40654,
			"2_stack": 41438,
			"3_stack": 42148
		},
		"Thought Harvester": {
			"1_stack": 41639,
			"2_stack": 41968,
			"3_stack": 42280
		},
		"Thunderous Blast": {
			"1_stack": 40836,
			"2_stack": 41635,
			"3_stack": 42485
		},
		"Tidal Surge": {
			"1_stack": 40715,
			"2_stack": 41446,
			"3_stack": 42188
		},
		"Tradewinds": {
			"1_stack": 40911,
			"2_stack": 41860,
			"3_stack": 42802
		},
		"Treacherous Covenant": {
			"1_stack": 41223,
			"2_stack": 42552,
			"3_stack": 43825
		},
		"Undulating Tides": {
			"1_stack": 41520,
			"2_stack": 43049,
			"3_stack": 44589
		},
		"Unstable Catalyst": {
			"1_stack": 40923,
			"2_stack": 41893,
			"3_stack": 42857
		},
		"Whispers of the Damned": {
			"1_stack": 41055,
			"2_stack": 41712,
			"3_stack": 42443
		},
		"Loyal to the End 4 Allies": {
			"1_stack": 41217,
			"2_stack": 42471,
			"3_stack": 43687
		},
		"Loyal to the End 3 Allies": {
			"1_stack": 41040,
			"2_stack": 42124,
			"3_stack": 43208
		},
		"Loyal to the End 2 Allies": {
			"1_stack": 40871,
			"2_stack": 41834,
			"3_stack": 42746
		},
		"Loyal to the End 1 Allies": {
			"1_stack": 40750,
			"2_stack": 41495,
			"3_stack": 42280
		},
		"Loyal to the End 0 Allies": {
			"1_stack": 40586,
			"2_stack": 41184,
			"3_stack": 41829
		},
		"Azerite Globules": {
			"1_stack": 40282,
			"2_stack": 40621,
			"3_stack": 40973
		},
		"Blood Siphon": {
			"1_stack": 40292,
			"2_stack": 40620,
			"3_stack": 40973
		},
		"Earthlink": {
			"1_stack": 40217,
			"2_stack": 40534,
			"3_stack": 40821
		},
		"Elemental Whirl": {
			"1_stack": 40436,
			"2_stack": 40928,
			"3_stack": 41413
		},
		"Gutripper": {
			"1_stack": 40468,
			"2_stack": 40954,
			"3_stack": 41452
		},
		"Heed My Call": {
			"1_stack": 40566,
			"2_stack": 41199,
			"3_stack": 41769
		},
		"On My Way": {
			"1_stack": 40428,
			"2_stack": 40854,
			"3_stack": 41333
		},
		"Overwhelming Power": {
			"1_stack": 40865,
			"2_stack": 41764,
			"3_stack": 42653
		},
		"Unstable Flames": {
			"1_stack": 40500,
			"2_stack": 41042,
			"3_stack": 41625
		},
		"Base": {
			"1_stack": 39952,
			"2_stack": 0,
			"3_stack": 0
		}
	},
	"Data_type": "traits",
	"spell_ids" : {
		"Ancients Bulwark ":"287631",
		"Apothecarys Concoctions ":"287604",
		"Arcane Heart ":"303006",
		"Archive of the Titans ":"280708",
		"Azerite Empowered ":"263978",
		"Azerite Globules ":"279955",
		"Barrage Of Many Bombs ":"280163",
		"Battlefield Focus ":"280582",
		"Blightborne Infusion ":"273823",
		"Blood Rite ":"280409",
		"Blood Siphon ":"264108",
		"Bonded Souls ":"288841",
		"Champion of Azeroth ":"270583",
		"Chorus of Insanity ":"278661",
		"Clockwork Heart ":"300210",
		"Collective Will ":"280837",
		"Combined Might ":"280848",
		"Dagger in the Back Behind ":"280285",
		"Dagger in the Back Front ":"280285",
		"Death Throes ":"278659",
		"Earthlink ":"279927",
		"Elemental Whirl ":"270667",
		"Endless Hunger ":"287662",
		"Fight or Flight ":"287818",
		"Filthy Transfusion ":"273836",
		"Glory in Battle ":"280852",
		"Gutripper ":"266937",
		"Heed My Call ":"271681",
		"Incite the Pack ":"280410",
		"Laser Matrix ":"280702",
		"Loyal to the End 4 Allies ":"303007",
		"Loyal to the End 3 Allies ":"303007",
		"Loyal to the End 2 Allies ":"303007",
		"Loyal to the End 1 Allies ":"303007",
		"Loyal to the End 0 Allies ":"303007",
		"Lifespeed":"267665",
		"Meticulous Scheming ":"273684",
		"On My Way ":"267879",
		"Overwhelming Power ":"266180",
		"Relational Normalization Gizmo ":"280178",
		"Retaliatory Fury ":"280785",
		"Rezans Fury ":"281834",
		"Ricocheting Inflatable Pyrosaw ":"280168",
		"Ruinous Bolt ":"280206",
		"Searing Dialogue ":"272788",
		"Secrets of the Deep ":"273829",
		"Shadow of Elune ": "287471" ,
		"Spiteful Apparitions ":"277682",
		"Swirling Sands ":"280433",
		"Sylvanas Resolve ":"280810",
		"Synaptic Spark Capacitor ":"280174",
		"Thought Harvester ":"273320",
		"Thunderous Blast ":"280384",
		"Tidal Surge ":"280404",
		"Tradewinds ":"281843",
		"Treacherous Covenant ":"288989",
		"Undulating Tides ":"303008",
		"Unstable Catalyst ":"281516",
		"Unstable Flames ":"279902",
		"Whispers of the Damned ":"275726"
	},
	"simulated_steps": [
		"1_stack",
		"2_stack",
		"3_stack"
	],
	"sorted_data_keys": [
		 "Chorus of Insanity",
		 "Thought Harvester",
		 "Blightborne Infusion",
		 "Ancients Bulwark",
		 "Undulating Tides",
		 "Champion of Azeroth",
		 "Swirling Sands",
		 "Barrage Of Many Bombs",
		 "Treacherous Covenant",
		 "Loyal to the End 4 Allies",
		 "Blood Rite",
		 "Whispers of the Damned",
		 "Clockwork Heart",
		 "Loyal to the End 3 Allies",
		 "Relational Normalization Gizmo",
		 "Meticulous Scheming",
		 "Unstable Catalyst",
		 "Tradewinds",
		 "Searing Dialogue",
		 "Glory in Battle",
		 "Loyal to the End 2 Allies",
		 "Overwhelming Power",
		 "Incite the Pack",
		 "Rezans Fury",
		 "Seductive Power",
		 "Secrets of the Deep",
		 "Thunderous Blast",
		 "Shadow of Elune",
		 "Sylvanas Resolve",
		 "Spiteful Apparitions",
		 "Death Throes",
		 "Loyal to the End 1 Allies",
		 "Dagger in the Back Behind",
		 "Tidal Surge",
		 "Filthy Transfusion",
		 "Ricocheting Inflatable Pyrosaw",
		 "Arcane Heart",
		 "Apothecarys Concoctions",
		 "Synaptic Spark Capacitor",
		 "Loyal to the End 0 Allies",
		 "Heed My Call",
		 "Battlefield Focus",
		 "Unstable Flames",
		 "Fight or Flight",
		 "Retaliatory Fury",
		 "Gutripper",
		 "Bonded Souls",
		 "Dagger in the Back Front",
		 "Elemental Whirl",
		 "On My Way",
		 "Ruinous Bolt",
		 "Collective Will",
		 "Combined Might",
		 "Blood Siphon",
		 "Azerite Globules",
		 "Earthlink"
	]
}