{
	"data": {
		"Searing Dialogue 3 Chorus of Insanity 2 Thought Harvester 1": {
			"1_stack": 29271
		},
		"Searing Dialogue 3 Chorus of Insanity 1 Thought Harvester 1 Whispers of the Damned 1": {
			"1_stack": 28765
		},
		"Searing Dialogue 3 Chorus of Insanity 1 Thought Harvester 1 Spiteful Apparitions 1": {
			"1_stack": 28660
		},
		"Searing Dialogue 3 Chorus of Insanity 3": {
			"1_stack": 28656
		},
		"Searing Dialogue 3 Death Throes 1 Thought Harvester 1 Barrage of Many Bombs 1": {
			"1_stack": 28630
		},
		"Searing Dialogue 3 Death Throes 2 Thought Harvester 1": {
			"1_stack": 28543
		},
		"Searing Dialogue 3 Spiteful Apparitions 1 Thought Harvester 1 Whispers of the Damned 1": {
			"1_stack": 27907
		},
		"Death Throes 3 Searing Dialogue 3": {
			"1_stack": 27740
		},
		"Chorus of Insanity 3 Spiteful Apparitions 2 Whispers of the Damned 1": {
			"1_stack": 27188
		},
		"Thought Harvester 3 Searing Dialogue 3": {
			"1_stack": 27126
		},
		"Death Throes 3 Chorus of Insanity 3": {
			"1_stack": 27091
		},
		"Whispers of the Damned 3 Chorus of Insanity 3": {
			"1_stack": 26805
		},
		"Spiteful Apparitions 3 Chorus of Insanity 3": {
			"1_stack": 26647
		},
		"Searing Dialogue 3 Spiteful Apparitions 3": {
			"1_stack": 26501
		},
		"Whispers of the Damned 3 Searing Dialogue 3": {
			"1_stack": 26388
		},
		"Thought Harvester 3 Chorus of Insanity 3": {
			"1_stack": 26203
		},
		"Thought Harvester 1 Searing Dialogue 2": {
			"1_stack": 25312
		},
		"Death Throes 3 Whispers of the Damned 3": {
			"1_stack": 25288
		},
		"Death Throes 3 Thought Harvester 3": {
			"1_stack": 24908
		},
		"Death Throes 3 Spiteful Apparitions 3": {
			"1_stack": 24867
		},
		"Chorus of Insanity 1 Searing Dialogue 2": {
			"1_stack": 24851
		},
		"Searing Dialogue 1 Chorus of Insanity 2": {
			"1_stack": 24758
		},
		"Death Throes 1 Searing Dialogue 2": {
			"1_stack": 24632
		},
		"Thought Harvester 1 Chorus of Insanity 2": {
			"1_stack": 24576
		},
		"Whispers of the Damned 1 Chorus of Insanity 2": {
			"1_stack": 24477
		},
		"Whispers of the Damned 1 Searing Dialogue 2": {
			"1_stack": 24423
		},
		"Whispers of the Damned 3 Thought Harvester 3": {
			"1_stack": 24421
		},
		"Death Throes 1 Chorus of Insanity 2": {
			"1_stack": 24324
		},
		"Spiteful Apparitions 1 Searing Dialogue 2": {
			"1_stack": 24235
		},
		"Thought Harvester 3 Spiteful Apparitions 3": {
			"1_stack": 24143
		},
		"Searing Dialogue 1 Death Throes 2": {
			"1_stack": 24134
		},
		"Spiteful Apparitions 1 Chorus of Insanity 2": {
			"1_stack": 24107
		},
		"Whispers of the Damned 3 Spiteful Apparitions 3": {
			"1_stack": 24103
		},
		"Searing Dialogue 1 Thought Harvester 2": {
			"1_stack": 24093
		},
		"Chorus of Insanity 1 Death Throes 2": {
			"1_stack": 24013
		},
		"Thought Harvester Searing Dialogue": {
			"1_stack": 23826
		},
		"Chorus of Insanity 1 Thought Harvester 2": {
			"1_stack": 23785
		},
		"Thought Harvester 1 Death Throes 2": {
			"1_stack": 23782
		},
		"Searing Dialogue Chorus of Insanity": {
			"1_stack": 23706
		},
		"Chorus of Insanity 1 Whispers of the Damned 2": {
			"1_stack": 23686
		},
		"Whispers of the Damned 1 Death Throes 2": {
			"1_stack": 23605
		},
		"Searing Dialogue 1 Whispers of the Damned 2": {
			"1_stack": 23576
		},
		"Thought Harvester Chorus of Insanity": {
			"1_stack": 23516
		},
		"Thought Harvester 1 Whispers of the Damned 2": {
			"1_stack": 23480
		},
		"Searing Dialogue 1 Spiteful Apparitions 2": {
			"1_stack": 23446
		},
		"Chorus of Insanity 1 Spiteful Apparitions 2": {
			"1_stack": 23415
		},
		"Death Throes Searing Dialogue": {
			"1_stack": 23378
		},
		"Death Throes 1 Thought Harvester 2": {
			"1_stack": 23366
		},
		"Whispers of the Damned 1 Thought Harvester 2": {
			"1_stack": 23334
		},
		"Spiteful Apparitions 1 Death Throes 2": {
			"1_stack": 23294
		},
		"Thought Harvester 1 Spiteful Apparitions 2": {
			"1_stack": 23262
		},
		"Whispers of the Damned Chorus of Insanity": {
			"1_stack": 23229
		},
		"Death Throes Chorus of Insanity": {
			"1_stack": 23216
		},
		"Death Throes 1 Whispers of the Damned 2": {
			"1_stack": 23196
		},
		"Spiteful Apparitions 1 Thought Harvester 2": {
			"1_stack": 23111
		},
		"Death Throes Thought Harvester": {
			"1_stack": 23111
		},
		"Whispers of the Damned Searing Dialogue": {
			"1_stack": 23102
		},
		"Whispers of the Damned Thought Harvester": {
			"1_stack": 23062
		},
		"Searing Dialogue Spiteful Apparitions": {
			"1_stack": 23011
		},
		"Spiteful Apparitions Chorus of Insanity": {
			"1_stack": 22943
		},
		"Death Throes 1 Spiteful Apparitions 2": {
			"1_stack": 22924
		},
		"Thought Harvester Spiteful Apparitions": {
			"1_stack": 22868
		},
		"Spiteful Apparitions 1 Whispers of the Damned 2": {
			"1_stack": 22833
		},
		"Whispers of the Damned 1 Spiteful Apparitions 2": {
			"1_stack": 22828
		},
		"Death Throes Whispers of the Damned": {
			"1_stack": 22804
		},
		"Death Throes Spiteful Apparitions": {
			"1_stack": 22527
		},
		"Whispers of the Damned Spiteful Apparitions": {
			"1_stack": 22432
		},
		"Base": {
			"1_stack": 21397,
		}
	},
	"sorted_data_keys": [
		"Searing Dialogue 3 Chorus of Insanity 2 Thought Harvester 1",
		"Searing Dialogue 3 Chorus of Insanity 1 Thought Harvester 1 Whispers of the Damned 1",
		"Searing Dialogue 3 Chorus of Insanity 1 Thought Harvester 1 Spiteful Apparitions 1",
		"Searing Dialogue 3 Chorus of Insanity 3",
		"Searing Dialogue 3 Death Throes 1 Thought Harvester 1 Barrage of Many Bombs 1",
		"Searing Dialogue 3 Death Throes 2 Thought Harvester 1",
		"Searing Dialogue 3 Spiteful Apparitions 1 Thought Harvester 1 Whispers of the Damned 1",
		"Death Throes 3 Searing Dialogue 3",
		"Chorus of Insanity 3 Spiteful Apparitions 2 Whispers of the Damned 1",
		"Thought Harvester 3 Searing Dialogue 3",
		"Death Throes 3 Chorus of Insanity 3",
		"Whispers of the Damned 3 Chorus of Insanity 3",
		"Spiteful Apparitions 3 Chorus of Insanity 3",
		"Searing Dialogue 3 Spiteful Apparitions 3",
		"Whispers of the Damned 3 Searing Dialogue 3",
		"Thought Harvester 3 Chorus of Insanity 3",
		"Thought Harvester 1 Searing Dialogue 2",
		"Death Throes 3 Whispers of the Damned 3",
		"Death Throes 3 Thought Harvester 3",
		"Death Throes 3 Spiteful Apparitions 3",
		"Chorus of Insanity 1 Searing Dialogue 2",
		"Searing Dialogue 1 Chorus of Insanity 2",
		"Death Throes 1 Searing Dialogue 2",
		"Thought Harvester 1 Chorus of Insanity 2",
		"Whispers of the Damned 1 Chorus of Insanity 2",
		"Whispers of the Damned 1 Searing Dialogue 2",
		"Whispers of the Damned 3 Thought Harvester 3",
		"Death Throes 1 Chorus of Insanity 2",
		"Spiteful Apparitions 1 Searing Dialogue 2",
		"Thought Harvester 3 Spiteful Apparitions 3",
		"Searing Dialogue 1 Death Throes 2",
		"Spiteful Apparitions 1 Chorus of Insanity 2",
		"Whispers of the Damned 3 Spiteful Apparitions 3",
		"Searing Dialogue 1 Thought Harvester 2",
		"Chorus of Insanity 1 Death Throes 2",
		"Thought Harvester Searing Dialogue",
		"Chorus of Insanity 1 Thought Harvester 2",
		"Thought Harvester 1 Death Throes 2",
		"Searing Dialogue Chorus of Insanity",
		"Chorus of Insanity 1 Whispers of the Damned 2",
		"Whispers of the Damned 1 Death Throes 2",
		"Searing Dialogue 1 Whispers of the Damned 2",
		"Thought Harvester Chorus of Insanity",
		"Thought Harvester 1 Whispers of the Damned 2",
		"Searing Dialogue 1 Spiteful Apparitions 2",
		"Chorus of Insanity 1 Spiteful Apparitions 2",
		"Death Throes Searing Dialogue",
		"Death Throes 1 Thought Harvester 2",
		"Whispers of the Damned 1 Thought Harvester 2",
		"Spiteful Apparitions 1 Death Throes 2",
		"Thought Harvester 1 Spiteful Apparitions 2",
		"Whispers of the Damned Chorus of Insanity",
		"Death Throes Chorus of Insanity",
		"Death Throes 1 Whispers of the Damned 2",
		"Spiteful Apparitions 1 Thought Harvester 2",
		"Death Throes Thought Harvester",
		"Whispers of the Damned Searing Dialogue",
		"Whispers of the Damned Thought Harvester",
		"Searing Dialogue Spiteful Apparitions",
		"Spiteful Apparitions Chorus of Insanity",
		"Death Throes 1 Spiteful Apparitions 2",
		"Thought Harvester Spiteful Apparitions",
		"Spiteful Apparitions 1 Whispers of the Damned 2",
		"Whispers of the Damned 1 Spiteful Apparitions 2",
		"Death Throes Whispers of the Damned",
		"Death Throes Spiteful Apparitions",
		"Whispers of the Damned Spiteful Apparitions"
	]
}