[
  {
    "profile": "composite",
    "actor": "Memory_of_Lucid_Dreams_3",
    "DPS": "49292",
    "increase": "11.46%",
    "": ""
  },
  {
    "profile": "composite",
    "actor": "Focused_Azerite_Beam_3",
    "DPS": "49206",
    "increase": "11.27%",
    "": ""
  },
  {
    "profile": "composite",
    "actor": "Focused_Azerite_Beam_2",
    "DPS": "49129",
    "increase": "11.09%",
    "": ""
  },
  {
    "profile": "composite",
    "actor": "Guardian_of_Azeroth_3",
    "DPS": "48749",
    "increase": "10.24%",
    "": ""
  },
  {
    "profile": "composite",
    "actor": "Blood_of_the_Enemy_100_Uptime_3",
    "DPS": "48606",
    "increase": "9.91%",
    "": ""
  },
  {
    "profile": "composite",
    "actor": "Focused_Azerite_Beam_1",
    "DPS": "48115",
    "increase": "8.80%",
    "": ""
  },
  {
    "profile": "composite",
    "actor": "Blood_of_the_Enemy_75_Uptime_3",
    "DPS": "47992",
    "increase": "8.52%",
    "": ""
  },
  {
    "profile": "composite",
    "actor": "Memory_of_Lucid_Dreams_2",
    "DPS": "47970",
    "increase": "8.47%",
    "": ""
  },
  {
    "profile": "composite",
    "actor": "Blood_of_the_Enemy_100_Uptime_2",
    "DPS": "47902",
    "increase": "8.32%",
    "": ""
  },
  {
    "profile": "composite",
    "actor": "Concentrated_Flame_3",
    "DPS": "47604",
    "increase": "7.65%",
    "": ""
  },
  {
    "profile": "composite",
    "actor": "Blood_of_the_Enemy_50_Uptime_3",
    "DPS": "47363",
    "increase": "7.10%",
    "": ""
  },
  {
    "profile": "composite",
    "actor": "Blood_of_the_Enemy_75_Uptime_2",
    "DPS": "47344",
    "increase": "7.06%",
    "": ""
  },
  {
    "profile": "composite",
    "actor": "Memory_of_Lucid_Dreams_1",
    "DPS": "47297",
    "increase": "6.95%",
    "": ""
  },
  {
    "profile": "composite",
    "actor": "Blood_of_the_Enemy_50_Uptime_2",
    "DPS": "46795",
    "increase": "5.82%",
    "": ""
  },
  {
    "profile": "composite",
    "actor": "Lifeblood_4_Allies_3",
    "DPS": "46773",
    "increase": "5.77%",
    "": ""
  },
  {
    "profile": "composite",
    "actor": "Lifeblood_3_Allies_3",
    "DPS": "46722",
    "increase": "5.65%",
    "": ""
  },
  {
    "profile": "composite",
    "actor": "Concentrated_Flame_2",
    "DPS": "46655",
    "increase": "5.50%",
    "": ""
  },
  {
    "profile": "composite",
    "actor": "Guardian_of_Azeroth_2",
    "DPS": "46635",
    "increase": "5.46%",
    "": ""
  },
  {
    "profile": "composite",
    "actor": "Lifeblood_4_Allies_2",
    "DPS": "46568",
    "increase": "5.30%",
    "": ""
  },
  {
    "profile": "composite",
    "actor": "Lifeblood_2_Allies_3",
    "DPS": "46512",
    "increase": "5.18%",
    "": ""
  },
  {
    "profile": "composite",
    "actor": "Lucid_Dreams_3",
    "DPS": "46498",
    "increase": "5.15%",
    "": ""
  },
  {
    "profile": "composite",
    "actor": "Focused_Energy_3",
    "DPS": "46442",
    "increase": "5.02%",
    "": ""
  },
  {
    "profile": "composite",
    "actor": "Purifying_Blast_3",
    "DPS": "46440",
    "increase": "5.01%",
    "": ""
  },
  {
    "profile": "composite",
    "actor": "Focused_Energy_2",
    "DPS": "46415",
    "increase": "4.96%",
    "": ""
  },
  {
    "profile": "composite",
    "actor": "Blood_of_the_Enemy_100_Uptime_1",
    "DPS": "46408",
    "increase": "4.94%",
    "": ""
  },
  {
    "profile": "composite",
    "actor": "Worldvein_Resonance_4_Allies_3",
    "DPS": "46355",
    "increase": "4.82%",
    "": ""
  },
  {
    "profile": "composite",
    "actor": "Lifeblood_3_Allies_2",
    "DPS": "46343",
    "increase": "4.80%",
    "": ""
  },
  {
    "profile": "composite",
    "actor": "Worldvein_Resonance_3_Allies_3",
    "DPS": "46307",
    "increase": "4.72%",
    "": ""
  },
  {
    "profile": "composite",
    "actor": "Blood_Soaked_3",
    "DPS": "46236",
    "increase": "4.55%",
    "": ""
  },
  {
    "profile": "composite",
    "actor": "Worldvein_Resonance_4_Allies_2",
    "DPS": "46219",
    "increase": "4.51%",
    "": ""
  },
  {
    "profile": "composite",
    "actor": "Ancient_Flame_3",
    "DPS": "46213",
    "increase": "4.50%",
    "": ""
  },
  {
    "profile": "composite",
    "actor": "Worldvein_Resonance_2_Allies_3",
    "DPS": "46178",
    "increase": "4.42%",
    "": ""
  },
  {
    "profile": "composite",
    "actor": "Purifying_Blast_1",
    "DPS": "46157",
    "increase": "4.38%",
    "": ""
  },
  {
    "profile": "composite",
    "actor": "Purifying_Blast_2",
    "DPS": "46153",
    "increase": "4.37%",
    "": ""
  },
  {
    "profile": "composite",
    "actor": "Conflict_3",
    "DPS": "46138",
    "increase": "4.33%",
    "": ""
  },
  {
    "profile": "composite",
    "actor": "Strife_3",
    "DPS": "46134",
    "increase": "4.32%",
    "": ""
  },
  {
    "profile": "composite",
    "actor": "Blood_Soaked_2",
    "DPS": "46093",
    "increase": "4.23%",
    "": ""
  },
  {
    "profile": "composite",
    "actor": "Worldvein_Resonance_3_Allies_2",
    "DPS": "46067",
    "increase": "4.17%",
    "": ""
  },
  {
    "profile": "composite",
    "actor": "Blood_of_the_Enemy_75_Uptime_1",
    "DPS": "46028",
    "increase": "4.08%",
    "": ""
  },
  {
    "profile": "composite",
    "actor": "Lifeblood_1_Allies_3",
    "DPS": "45969",
    "increase": "3.95%",
    "": ""
  },
  {
    "profile": "composite",
    "actor": "Lifeblood_4_Allies_1",
    "DPS": "45945",
    "increase": "3.90%",
    "": ""
  },
  {
    "profile": "composite",
    "actor": "Guardian_of_Azeroth_1",
    "DPS": "45905",
    "increase": "3.80%",
    "": ""
  },
  {
    "profile": "composite",
    "actor": "Condensed_Life_Force_3",
    "DPS": "45903",
    "increase": "3.80%",
    "": ""
  },
  {
    "profile": "composite",
    "actor": "Lifeblood_2_Allies_2",
    "DPS": "45812",
    "increase": "3.60%",
    "": ""
  },
  {
    "profile": "composite",
    "actor": "The_Unbound_Force_3",
    "DPS": "45791",
    "increase": "3.55%",
    "": ""
  },
  {
    "profile": "composite",
    "actor": "Worldvein_Resonance_1_Allies_3",
    "DPS": "45774",
    "increase": "3.51%",
    "": ""
  },
  {
    "profile": "composite",
    "actor": "Concentrated_Flame_1",
    "DPS": "45683",
    "increase": "3.30%",
    "": ""
  },
  {
    "profile": "composite",
    "actor": "Worldvein_Resonance_2_Allies_2",
    "DPS": "45675",
    "increase": "3.29%",
    "": ""
  },
  {
    "profile": "composite",
    "actor": "Focused_Energy_1",
    "DPS": "45670",
    "increase": "3.27%",
    "": ""
  },
  {
    "profile": "composite",
    "actor": "Lifeblood_3_Allies_1",
    "DPS": "45660",
    "increase": "3.25%",
    "": ""
  },
  {
    "profile": "composite",
    "actor": "Vision_of_Perfection_3",
    "DPS": "45641",
    "increase": "3.21%",
    "": ""
  },
  {
    "profile": "composite",
    "actor": "Blood_of_the_Enemy_50_Uptime_1",
    "DPS": "45638",
    "increase": "3.20%",
    "": ""
  },
  {
    "profile": "composite",
    "actor": "Worldvein_Resonance_4_Allies_1",
    "DPS": "45626",
    "increase": "3.17%",
    "": ""
  },
  {
    "profile": "composite",
    "actor": "Purification_Protocol_3",
    "DPS": "45601",
    "increase": "3.12%",
    "": ""
  },
  {
    "profile": "composite",
    "actor": "Strife_2",
    "DPS": "45495",
    "increase": "2.88%",
    "": ""
  },
  {
    "profile": "composite",
    "actor": "Conflict_2",
    "DPS": "45489",
    "increase": "2.86%",
    "": ""
  },
  {
    "profile": "composite",
    "actor": "Worldvein_Resonance_3_Allies_1",
    "DPS": "45377",
    "increase": "2.61%",
    "": ""
  },
  {
    "profile": "composite",
    "actor": "Ancient_Flame_2",
    "DPS": "45355",
    "increase": "2.56%",
    "": ""
  },
  {
    "profile": "composite",
    "actor": "Condensed_Life_Force_2",
    "DPS": "45331",
    "increase": "2.51%",
    "": ""
  },
  {
    "profile": "composite",
    "actor": "Purification_Protocol_1",
    "DPS": "45326",
    "increase": "2.50%",
    "": ""
  },
  {
    "profile": "composite",
    "actor": "Ripple_in_Space_2",
    "DPS": "45324",
    "increase": "2.49%",
    "": ""
  },
  {
    "profile": "composite",
    "actor": "Purification_Protocol_2",
    "DPS": "45324",
    "increase": "2.49%",
    "": ""
  },
  {
    "profile": "composite",
    "actor": "Ripple_in_Space_3",
    "DPS": "45317",
    "increase": "2.48%",
    "": ""
  },
  {
    "profile": "composite",
    "actor": "Lifeblood_2_Allies_1",
    "DPS": "45300",
    "increase": "2.44%",
    "": ""
  },
  {
    "profile": "composite",
    "actor": "Vision_of_Perfection_2",
    "DPS": "45300",
    "increase": "2.44%",
    "": ""
  },
  {
    "profile": "composite",
    "actor": "Lucid_Dreams_1",
    "DPS": "45298",
    "increase": "2.43%",
    "": ""
  },
  {
    "profile": "composite",
    "actor": "Lucid_Dreams_2",
    "DPS": "45291",
    "increase": "2.42%",
    "": ""
  },
  {
    "profile": "composite",
    "actor": "Lifeblood_1_Allies_2",
    "DPS": "45286",
    "increase": "2.40%",
    "": ""
  },
  {
    "profile": "composite",
    "actor": "Worldvein_Resonance_1_Allies_2",
    "DPS": "45276",
    "increase": "2.38%",
    "": ""
  },
  {
    "profile": "composite",
    "actor": "Reckless_Force_3",
    "DPS": "45157",
    "increase": "2.11%",
    "": ""
  },
  {
    "profile": "composite",
    "actor": "Blood_Soaked_1",
    "DPS": "45149",
    "increase": "2.10%",
    "": ""
  },
  {
    "profile": "composite",
    "actor": "Ripple_in_Space_1",
    "DPS": "45139",
    "increase": "2.07%",
    "": ""
  },
  {
    "profile": "composite",
    "actor": "Ancient_Flame_1",
    "DPS": "45125",
    "increase": "2.04%",
    "": ""
  },
  {
    "profile": "composite",
    "actor": "Condensed_Life_Force_1",
    "DPS": "45110",
    "increase": "2.01%",
    "": ""
  },
  {
    "profile": "composite",
    "actor": "Worldvein_Resonance_2_Allies_1",
    "DPS": "45071",
    "increase": "1.92%",
    "": ""
  },
  {
    "profile": "composite",
    "actor": "The_Unbound_Force_2",
    "DPS": "45047",
    "increase": "1.87%",
    "": ""
  },
  {
    "profile": "composite",
    "actor": "Vision_of_Perfection_1",
    "DPS": "45016",
    "increase": "1.79%",
    "": ""
  },
  {
    "profile": "composite",
    "actor": "Conflict_1",
    "DPS": "45013",
    "increase": "1.79%",
    "": ""
  },
  {
    "profile": "composite",
    "actor": "Strife_1",
    "DPS": "45006",
    "increase": "1.77%",
    "": ""
  },
  {
    "profile": "composite",
    "actor": "The_Unbound_Force_1",
    "DPS": "44971",
    "increase": "1.69%",
    "": ""
  },
  {
    "profile": "composite",
    "actor": "Lifeblood_1_Allies_1",
    "DPS": "44944",
    "increase": "1.63%",
    "": ""
  },
  {
    "profile": "composite",
    "actor": "Reckless_Force_2",
    "DPS": "44931",
    "increase": "1.60%",
    "": ""
  },
  {
    "profile": "composite",
    "actor": "Reckless_Force_1",
    "DPS": "44822",
    "increase": "1.36%",
    "": ""
  },
  {
    "profile": "composite",
    "actor": "Worldvein_Resonance_1_Allies_1",
    "DPS": "44733",
    "increase": "1.16%",
    "": ""
  },
  {
    "profile": "composite",
    "actor": "Strive_for_Perfection_3",
    "DPS": "44572",
    "increase": "0.79%",
    "": ""
  },
  {
    "profile": "composite",
    "actor": "Strive_for_Perfection_2",
    "DPS": "44374",
    "increase": "0.34%",
    "": ""
  },
  {
    "profile": "composite",
    "actor": "Strive_for_Perfection_1",
    "DPS": "44364",
    "increase": "0.32%",
    "": ""
  },
  {
    "profile": "composite",
    "actor": "Base",
    "DPS": "44222",
    "increase": "0.00%",
    "": ""
  },
  {
    "profile": "single_target",
    "actor": "Guardian_of_Azeroth_3",
    "DPS": "43353",
    "increase": "11.23%",
    "": ""
  },
  {
    "profile": "single_target",
    "actor": "Memory_of_Lucid_Dreams_3",
    "DPS": "43220",
    "increase": "10.89%",
    "": ""
  },
  {
    "profile": "single_target",
    "actor": "Concentrated_Flame_3",
    "DPS": "42573",
    "increase": "9.23%",
    "": ""
  },
  {
    "profile": "single_target",
    "actor": "Blood_of_the_Enemy_100_Uptime_3",
    "DPS": "42368",
    "increase": "8.70%",
    "": ""
  },
  {
    "profile": "single_target",
    "actor": "Focused_Azerite_Beam_3",
    "DPS": "42107",
    "increase": "8.04%",
    "": ""
  },
  {
    "profile": "single_target",
    "actor": "Memory_of_Lucid_Dreams_2",
    "DPS": "42048",
    "increase": "7.88%",
    "": ""
  },
  {
    "profile": "single_target",
    "actor": "Focused_Azerite_Beam_2",
    "DPS": "42017",
    "increase": "7.81%",
    "": ""
  },
  {
    "profile": "single_target",
    "actor": "Blood_of_the_Enemy_75_Uptime_3",
    "DPS": "41927",
    "increase": "7.57%",
    "": ""
  },
  {
    "profile": "single_target",
    "actor": "Blood_of_the_Enemy_100_Uptime_2",
    "DPS": "41818",
    "increase": "7.29%",
    "": ""
  },
  {
    "profile": "single_target",
    "actor": "Concentrated_Flame_2",
    "DPS": "41495",
    "increase": "6.47%",
    "": ""
  },
  {
    "profile": "single_target",
    "actor": "Blood_of_the_Enemy_50_Uptime_3",
    "DPS": "41476",
    "increase": "6.42%",
    "": ""
  },
  {
    "profile": "single_target",
    "actor": "Memory_of_Lucid_Dreams_1",
    "DPS": "41476",
    "increase": "6.42%",
    "": ""
  },
  {
    "profile": "single_target",
    "actor": "Blood_of_the_Enemy_75_Uptime_2",
    "DPS": "41402",
    "increase": "6.23%",
    "": ""
  },
  {
    "profile": "single_target",
    "actor": "Guardian_of_Azeroth_2",
    "DPS": "41311",
    "increase": "5.99%",
    "": ""
  },
  {
    "profile": "single_target",
    "actor": "Lifeblood_4_Allies_3",
    "DPS": "41195",
    "increase": "5.70%",
    "": ""
  },
  {
    "profile": "single_target",
    "actor": "Focused_Azerite_Beam_1",
    "DPS": "41164",
    "increase": "5.62%",
    "": ""
  },
  {
    "profile": "single_target",
    "actor": "Lifeblood_3_Allies_3",
    "DPS": "41162",
    "increase": "5.61%",
    "": ""
  },
  {
    "profile": "single_target",
    "actor": "Ancient_Flame_3",
    "DPS": "41026",
    "increase": "5.26%",
    "": ""
  },
  {
    "profile": "single_target",
    "actor": "Lifeblood_4_Allies_2",
    "DPS": "41012",
    "increase": "5.23%",
    "": ""
  },
  {
    "profile": "single_target",
    "actor": "Blood_of_the_Enemy_50_Uptime_2",
    "DPS": "40992",
    "increase": "5.18%",
    "": ""
  },
  {
    "profile": "single_target",
    "actor": "Lucid_Dreams_3",
    "DPS": "40973",
    "increase": "5.13%",
    "": ""
  },
  {
    "profile": "single_target",
    "actor": "Lifeblood_2_Allies_3",
    "DPS": "40967",
    "increase": "5.11%",
    "": ""
  },
  {
    "profile": "single_target",
    "actor": "Focused_Energy_3",
    "DPS": "40937",
    "increase": "5.03%",
    "": ""
  },
  {
    "profile": "single_target",
    "actor": "Focused_Energy_2",
    "DPS": "40914",
    "increase": "4.98%",
    "": ""
  },
  {
    "profile": "single_target",
    "actor": "Lifeblood_3_Allies_2",
    "DPS": "40814",
    "increase": "4.72%",
    "": ""
  },
  {
    "profile": "single_target",
    "actor": "Worldvein_Resonance_4_Allies_3",
    "DPS": "40807",
    "increase": "4.70%",
    "": ""
  },
  {
    "profile": "single_target",
    "actor": "Blood_of_the_Enemy_100_Uptime_1",
    "DPS": "40771",
    "increase": "4.61%",
    "": ""
  },
  {
    "profile": "single_target",
    "actor": "Worldvein_Resonance_3_Allies_3",
    "DPS": "40761",
    "increase": "4.58%",
    "": ""
  },
  {
    "profile": "single_target",
    "actor": "Condensed_Life_Force_3",
    "DPS": "40687",
    "increase": "4.39%",
    "": ""
  },
  {
    "profile": "single_target",
    "actor": "Worldvein_Resonance_4_Allies_2",
    "DPS": "40679",
    "increase": "4.37%",
    "": ""
  },
  {
    "profile": "single_target",
    "actor": "Guardian_of_Azeroth_1",
    "DPS": "40658",
    "increase": "4.32%",
    "": ""
  },
  {
    "profile": "single_target",
    "actor": "Worldvein_Resonance_2_Allies_3",
    "DPS": "40652",
    "increase": "4.30%",
    "": ""
  },
  {
    "profile": "single_target",
    "actor": "Conflict_3",
    "DPS": "40651",
    "increase": "4.30%",
    "": ""
  },
  {
    "profile": "single_target",
    "actor": "Blood_Soaked_3",
    "DPS": "40646",
    "increase": "4.29%",
    "": ""
  },
  {
    "profile": "single_target",
    "actor": "Strife_3",
    "DPS": "40638",
    "increase": "4.27%",
    "": ""
  },
  {
    "profile": "single_target",
    "actor": "Worldvein_Resonance_3_Allies_2",
    "DPS": "40551",
    "increase": "4.04%",
    "": ""
  },
  {
    "profile": "single_target",
    "actor": "Blood_Soaked_2",
    "DPS": "40538",
    "increase": "4.01%",
    "": ""
  },
  {
    "profile": "single_target",
    "actor": "Concentrated_Flame_1",
    "DPS": "40520",
    "increase": "3.96%",
    "": ""
  },
  {
    "profile": "single_target",
    "actor": "The_Unbound_Force_3",
    "DPS": "40503",
    "increase": "3.92%",
    "": ""
  },
  {
    "profile": "single_target",
    "actor": "Lifeblood_1_Allies_3",
    "DPS": "40490",
    "increase": "3.89%",
    "": ""
  },
  {
    "profile": "single_target",
    "actor": "Lifeblood_4_Allies_1",
    "DPS": "40475",
    "increase": "3.85%",
    "": ""
  },
  {
    "profile": "single_target",
    "actor": "Blood_of_the_Enemy_75_Uptime_1",
    "DPS": "40438",
    "increase": "3.75%",
    "": ""
  },
  {
    "profile": "single_target",
    "actor": "Purifying_Blast_3",
    "DPS": "40428",
    "increase": "3.73%",
    "": ""
  },
  {
    "profile": "single_target",
    "actor": "Lifeblood_2_Allies_2",
    "DPS": "40364",
    "increase": "3.56%",
    "": ""
  },
  {
    "profile": "single_target",
    "actor": "Worldvein_Resonance_1_Allies_3",
    "DPS": "40300",
    "increase": "3.40%",
    "": ""
  },
  {
    "profile": "single_target",
    "actor": "Vision_of_Perfection_3",
    "DPS": "40276",
    "increase": "3.34%",
    "": ""
  },
  {
    "profile": "single_target",
    "actor": "Focused_Energy_1",
    "DPS": "40257",
    "increase": "3.29%",
    "": ""
  },
  {
    "profile": "single_target",
    "actor": "Purifying_Blast_1",
    "DPS": "40235",
    "increase": "3.23%",
    "": ""
  },
  {
    "profile": "single_target",
    "actor": "Purifying_Blast_2",
    "DPS": "40232",
    "increase": "3.23%",
    "": ""
  },
  {
    "profile": "single_target",
    "actor": "Lifeblood_3_Allies_1",
    "DPS": "40225",
    "increase": "3.21%",
    "": ""
  },
  {
    "profile": "single_target",
    "actor": "Worldvein_Resonance_2_Allies_2",
    "DPS": "40215",
    "increase": "3.18%",
    "": ""
  },
  {
    "profile": "single_target",
    "actor": "Worldvein_Resonance_4_Allies_1",
    "DPS": "40166",
    "increase": "3.06%",
    "": ""
  },
  {
    "profile": "single_target",
    "actor": "Blood_of_the_Enemy_50_Uptime_1",
    "DPS": "40090",
    "increase": "2.86%",
    "": ""
  },
  {
    "profile": "single_target",
    "actor": "Strife_2",
    "DPS": "40080",
    "increase": "2.83%",
    "": ""
  },
  {
    "profile": "single_target",
    "actor": "Condensed_Life_Force_2",
    "DPS": "40072",
    "increase": "2.81%",
    "": ""
  },
  {
    "profile": "single_target",
    "actor": "Conflict_2",
    "DPS": "40072",
    "increase": "2.81%",
    "": ""
  },
  {
    "profile": "single_target",
    "actor": "Ancient_Flame_2",
    "DPS": "40033",
    "increase": "2.71%",
    "": ""
  },
  {
    "profile": "single_target",
    "actor": "Vision_of_Perfection_2",
    "DPS": "39969",
    "increase": "2.55%",
    "": ""
  },
  {
    "profile": "single_target",
    "actor": "Worldvein_Resonance_3_Allies_1",
    "DPS": "39958",
    "increase": "2.52%",
    "": ""
  },
  {
    "profile": "single_target",
    "actor": "Lifeblood_2_Allies_1",
    "DPS": "39906",
    "increase": "2.39%",
    "": ""
  },
  {
    "profile": "single_target",
    "actor": "Lucid_Dreams_1",
    "DPS": "39906",
    "increase": "2.39%",
    "": ""
  },
  {
    "profile": "single_target",
    "actor": "Purification_Protocol_3",
    "DPS": "39892",
    "increase": "2.35%",
    "": ""
  },
  {
    "profile": "single_target",
    "actor": "Lucid_Dreams_2",
    "DPS": "39890",
    "increase": "2.35%",
    "": ""
  },
  {
    "profile": "single_target",
    "actor": "Lifeblood_1_Allies_2",
    "DPS": "39886",
    "increase": "2.34%",
    "": ""
  },
  {
    "profile": "single_target",
    "actor": "Worldvein_Resonance_1_Allies_2",
    "DPS": "39862",
    "increase": "2.28%",
    "": ""
  },
  {
    "profile": "single_target",
    "actor": "Condensed_Life_Force_1",
    "DPS": "39846",
    "increase": "2.24%",
    "": ""
  },
  {
    "profile": "single_target",
    "actor": "Ancient_Flame_1",
    "DPS": "39821",
    "increase": "2.17%",
    "": ""
  },
  {
    "profile": "single_target",
    "actor": "Ripple_in_Space_2",
    "DPS": "39795",
    "increase": "2.10%",
    "": ""
  },
  {
    "profile": "single_target",
    "actor": "Ripple_in_Space_3",
    "DPS": "39793",
    "increase": "2.10%",
    "": ""
  },
  {
    "profile": "single_target",
    "actor": "The_Unbound_Force_2",
    "DPS": "39777",
    "increase": "2.06%",
    "": ""
  },
  {
    "profile": "single_target",
    "actor": "Reckless_Force_3",
    "DPS": "39726",
    "increase": "1.93%",
    "": ""
  },
  {
    "profile": "single_target",
    "actor": "Blood_Soaked_1",
    "DPS": "39725",
    "increase": "1.92%",
    "": ""
  },
  {
    "profile": "single_target",
    "actor": "Purification_Protocol_2",
    "DPS": "39716",
    "increase": "1.90%",
    "": ""
  },
  {
    "profile": "single_target",
    "actor": "Purification_Protocol_1",
    "DPS": "39715",
    "increase": "1.90%",
    "": ""
  },
  {
    "profile": "single_target",
    "actor": "Vision_of_Perfection_1",
    "DPS": "39705",
    "increase": "1.87%",
    "": ""
  },
  {
    "profile": "single_target",
    "actor": "Worldvein_Resonance_2_Allies_1",
    "DPS": "39683",
    "increase": "1.82%",
    "": ""
  },
  {
    "profile": "single_target",
    "actor": "Conflict_1",
    "DPS": "39657",
    "increase": "1.75%",
    "": ""
  },
  {
    "profile": "single_target",
    "actor": "Strife_1",
    "DPS": "39651",
    "increase": "1.73%",
    "": ""
  },
  {
    "profile": "single_target",
    "actor": "The_Unbound_Force_1",
    "DPS": "39632",
    "increase": "1.69%",
    "": ""
  },
  {
    "profile": "single_target",
    "actor": "Ripple_in_Space_1",
    "DPS": "39630",
    "increase": "1.68%",
    "": ""
  },
  {
    "profile": "single_target",
    "actor": "Lifeblood_1_Allies_1",
    "DPS": "39593",
    "increase": "1.59%",
    "": ""
  },
  {
    "profile": "single_target",
    "actor": "Reckless_Force_2",
    "DPS": "39540",
    "increase": "1.45%",
    "": ""
  },
  {
    "profile": "single_target",
    "actor": "Reckless_Force_1",
    "DPS": "39461",
    "increase": "1.25%",
    "": ""
  },
  {
    "profile": "single_target",
    "actor": "Worldvein_Resonance_1_Allies_1",
    "DPS": "39394",
    "increase": "1.07%",
    "": ""
  },
  {
    "profile": "single_target",
    "actor": "Strive_for_Perfection_3",
    "DPS": "39255",
    "increase": "0.72%",
    "": ""
  },
  {
    "profile": "single_target",
    "actor": "Strive_for_Perfection_2",
    "DPS": "39087",
    "increase": "0.29%",
    "": ""
  },
  {
    "profile": "single_target",
    "actor": "Strive_for_Perfection_1",
    "DPS": "39081",
    "increase": "0.27%",
    "": ""
  },
  {
    "profile": "single_target",
    "actor": "Base",
    "DPS": "38975",
    "increase": "0.00%",
    "": ""
  }
]