[
  {
    "profile": "composite",
    "actor": "Memory_of_Lucid_Dreams_3",
    "DPS": "49376",
    "increase": "10.78%",
    "": ""
  },
  {
    "profile": "composite",
    "actor": "Guardian_of_Azeroth_3",
    "DPS": "49105",
    "increase": "10.17%",
    "": ""
  },
  {
    "profile": "composite",
    "actor": "Focused_Azerite_Beam_3",
    "DPS": "48901",
    "increase": "9.71%",
    "": ""
  },
  {
    "profile": "composite",
    "actor": "Blood_of_the_Enemy_100_Uptime_3",
    "DPS": "48883",
    "increase": "9.67%",
    "": ""
  },
  {
    "profile": "composite",
    "actor": "Focused_Azerite_Beam_2",
    "DPS": "48832",
    "increase": "9.56%",
    "": ""
  },
  {
    "profile": "composite",
    "actor": "Blood_of_the_Enemy_75_Uptime_3",
    "DPS": "48258",
    "increase": "8.27%",
    "": ""
  },
  {
    "profile": "composite",
    "actor": "Blood_of_the_Enemy_100_Uptime_2",
    "DPS": "48125",
    "increase": "7.97%",
    "": ""
  },
  {
    "profile": "composite",
    "actor": "Memory_of_Lucid_Dreams_2",
    "DPS": "48076",
    "increase": "7.86%",
    "": ""
  },
  {
    "profile": "composite",
    "actor": "Concentrated_Flame_3",
    "DPS": "47915",
    "increase": "7.50%",
    "": ""
  },
  {
    "profile": "composite",
    "actor": "Focused_Azerite_Beam_1",
    "DPS": "47790",
    "increase": "7.22%",
    "": ""
  },
  {
    "profile": "composite",
    "actor": "Blood_of_the_Enemy_50_Uptime_3",
    "DPS": "47655",
    "increase": "6.91%",
    "": ""
  },
  {
    "profile": "composite",
    "actor": "Blood_of_the_Enemy_75_Uptime_2",
    "DPS": "47592",
    "increase": "6.77%",
    "": ""
  },
  {
    "profile": "composite",
    "actor": "Memory_of_Lucid_Dreams_1",
    "DPS": "47499",
    "increase": "6.56%",
    "": ""
  },
  {
    "profile": "composite",
    "actor": "Lifeblood_4_Allies_3",
    "DPS": "47107",
    "increase": "5.69%",
    "": ""
  },
  {
    "profile": "composite",
    "actor": "Lifeblood_3_Allies_3",
    "DPS": "47054",
    "increase": "5.57%",
    "": ""
  },
  {
    "profile": "composite",
    "actor": "Blood_of_the_Enemy_50_Uptime_2",
    "DPS": "47050",
    "increase": "5.56%",
    "": ""
  },
  {
    "profile": "composite",
    "actor": "Guardian_of_Azeroth_2",
    "DPS": "46978",
    "increase": "5.40%",
    "": ""
  },
  {
    "profile": "composite",
    "actor": "Concentrated_Flame_2",
    "DPS": "46969",
    "increase": "5.37%",
    "": ""
  },
  {
    "profile": "composite",
    "actor": "Lifeblood_4_Allies_2",
    "DPS": "46906",
    "increase": "5.23%",
    "": ""
  },
  {
    "profile": "composite",
    "actor": "Lucid_Dreams_3",
    "DPS": "46850",
    "increase": "5.11%",
    "": ""
  },
  {
    "profile": "composite",
    "actor": "Lifeblood_2_Allies_3",
    "DPS": "46844",
    "increase": "5.10%",
    "": ""
  },
  {
    "profile": "composite",
    "actor": "Purifying_Blast_3",
    "DPS": "46759",
    "increase": "4.90%",
    "": ""
  },
  {
    "profile": "composite",
    "actor": "Focused_Energy_3",
    "DPS": "46727",
    "increase": "4.83%",
    "": ""
  },
  {
    "profile": "composite",
    "actor": "Blood_of_the_Enemy_100_Uptime_1",
    "DPS": "46681",
    "increase": "4.73%",
    "": ""
  },
  {
    "profile": "composite",
    "actor": "Focused_Energy_2",
    "DPS": "46680",
    "increase": "4.73%",
    "": ""
  },
  {
    "profile": "composite",
    "actor": "Lifeblood_3_Allies_2",
    "DPS": "46675",
    "increase": "4.71%",
    "": ""
  },
  {
    "profile": "composite",
    "actor": "Worldvein_Resonance_4_Allies_3",
    "DPS": "46655",
    "increase": "4.67%",
    "": ""
  },
  {
    "profile": "composite",
    "actor": "Worldvein_Resonance_3_Allies_3",
    "DPS": "46629",
    "increase": "4.61%",
    "": ""
  },
  {
    "profile": "composite",
    "actor": "Ancient_Flame_3",
    "DPS": "46553",
    "increase": "4.44%",
    "": ""
  },
  {
    "profile": "composite",
    "actor": "Worldvein_Resonance_4_Allies_2",
    "DPS": "46528",
    "increase": "4.39%",
    "": ""
  },
  {
    "profile": "composite",
    "actor": "Conflict_3",
    "DPS": "46505",
    "increase": "4.33%",
    "": ""
  },
  {
    "profile": "composite",
    "actor": "Strife_3",
    "DPS": "46502",
    "increase": "4.33%",
    "": ""
  },
  {
    "profile": "composite",
    "actor": "Worldvein_Resonance_2_Allies_3",
    "DPS": "46495",
    "increase": "4.31%",
    "": ""
  },
  {
    "profile": "composite",
    "actor": "Blood_Soaked_3",
    "DPS": "46488",
    "increase": "4.30%",
    "": ""
  },
  {
    "profile": "composite",
    "actor": "Purifying_Blast_1",
    "DPS": "46487",
    "increase": "4.29%",
    "": ""
  },
  {
    "profile": "composite",
    "actor": "Purifying_Blast_2",
    "DPS": "46478",
    "increase": "4.27%",
    "": ""
  },
  {
    "profile": "composite",
    "actor": "Worldvein_Resonance_3_Allies_2",
    "DPS": "46375",
    "increase": "4.04%",
    "": ""
  },
  {
    "profile": "composite",
    "actor": "Blood_Soaked_2",
    "DPS": "46363",
    "increase": "4.02%",
    "": ""
  },
  {
    "profile": "composite",
    "actor": "Blood_of_the_Enemy_75_Uptime_1",
    "DPS": "46316",
    "increase": "3.91%",
    "": ""
  },
  {
    "profile": "composite",
    "actor": "Lifeblood_1_Allies_3",
    "DPS": "46309",
    "increase": "3.89%",
    "": ""
  },
  {
    "profile": "composite",
    "actor": "Lifeblood_4_Allies_1",
    "DPS": "46285",
    "increase": "3.84%",
    "": ""
  },
  {
    "profile": "composite",
    "actor": "Guardian_of_Azeroth_1",
    "DPS": "46254",
    "increase": "3.77%",
    "": ""
  },
  {
    "profile": "composite",
    "actor": "Condensed_Life_Force_3",
    "DPS": "46247",
    "increase": "3.76%",
    "": ""
  },
  {
    "profile": "composite",
    "actor": "Lifeblood_2_Allies_2",
    "DPS": "46159",
    "increase": "3.56%",
    "": ""
  },
  {
    "profile": "composite",
    "actor": "Worldvein_Resonance_1_Allies_3",
    "DPS": "46090",
    "increase": "3.40%",
    "": ""
  },
  {
    "profile": "composite",
    "actor": "The_Unbound_Force_3",
    "DPS": "46077",
    "increase": "3.37%",
    "": ""
  },
  {
    "profile": "composite",
    "actor": "Lifeblood_3_Allies_1",
    "DPS": "46007",
    "increase": "3.22%",
    "": ""
  },
  {
    "profile": "composite",
    "actor": "Concentrated_Flame_1",
    "DPS": "45993",
    "increase": "3.18%",
    "": ""
  },
  {
    "profile": "composite",
    "actor": "Worldvein_Resonance_2_Allies_2",
    "DPS": "45984",
    "increase": "3.17%",
    "": ""
  },
  {
    "profile": "composite",
    "actor": "Vision_of_Perfection_3",
    "DPS": "45980",
    "increase": "3.16%",
    "": ""
  },
  {
    "profile": "composite",
    "actor": "Focused_Energy_1",
    "DPS": "45975",
    "increase": "3.15%",
    "": ""
  },
  {
    "profile": "composite",
    "actor": "Blood_of_the_Enemy_50_Uptime_1",
    "DPS": "45953",
    "increase": "3.09%",
    "": ""
  },
  {
    "profile": "composite",
    "actor": "Worldvein_Resonance_4_Allies_1",
    "DPS": "45946",
    "increase": "3.08%",
    "": ""
  },
  {
    "profile": "composite",
    "actor": "Purification_Protocol_3",
    "DPS": "45936",
    "increase": "3.06%",
    "": ""
  },
  {
    "profile": "composite",
    "actor": "Strife_2",
    "DPS": "45848",
    "increase": "2.86%",
    "": ""
  },
  {
    "profile": "composite",
    "actor": "Conflict_2",
    "DPS": "45844",
    "increase": "2.85%",
    "": ""
  },
  {
    "profile": "composite",
    "actor": "Worldvein_Resonance_3_Allies_1",
    "DPS": "45697",
    "increase": "2.52%",
    "": ""
  },
  {
    "profile": "composite",
    "actor": "Ancient_Flame_2",
    "DPS": "45689",
    "increase": "2.50%",
    "": ""
  },
  {
    "profile": "composite",
    "actor": "Purification_Protocol_2",
    "DPS": "45668",
    "increase": "2.46%",
    "": ""
  },
  {
    "profile": "composite",
    "actor": "Condensed_Life_Force_2",
    "DPS": "45667",
    "increase": "2.45%",
    "": ""
  },
  {
    "profile": "composite",
    "actor": "Purification_Protocol_1",
    "DPS": "45660",
    "increase": "2.44%",
    "": ""
  },
  {
    "profile": "composite",
    "actor": "Lucid_Dreams_2",
    "DPS": "45653",
    "increase": "2.42%",
    "": ""
  },
  {
    "profile": "composite",
    "actor": "Lucid_Dreams_1",
    "DPS": "45651",
    "increase": "2.42%",
    "": ""
  },
  {
    "profile": "composite",
    "actor": "Ripple_in_Space_2",
    "DPS": "45639",
    "increase": "2.39%",
    "": ""
  },
  {
    "profile": "composite",
    "actor": "Ripple_in_Space_3",
    "DPS": "45638",
    "increase": "2.39%",
    "": ""
  },
  {
    "profile": "composite",
    "actor": "Vision_of_Perfection_2",
    "DPS": "45637",
    "increase": "2.39%",
    "": ""
  },
  {
    "profile": "composite",
    "actor": "Lifeblood_2_Allies_1",
    "DPS": "45636",
    "increase": "2.39%",
    "": ""
  },
  {
    "profile": "composite",
    "actor": "Lifeblood_1_Allies_2",
    "DPS": "45624",
    "increase": "2.36%",
    "": ""
  },
  {
    "profile": "composite",
    "actor": "Worldvein_Resonance_1_Allies_2",
    "DPS": "45597",
    "increase": "2.30%",
    "": ""
  },
  {
    "profile": "composite",
    "actor": "Blood_Soaked_1",
    "DPS": "45486",
    "increase": "2.05%",
    "": ""
  },
  {
    "profile": "composite",
    "actor": "Ancient_Flame_1",
    "DPS": "45463",
    "increase": "2.00%",
    "": ""
  },
  {
    "profile": "composite",
    "actor": "Ripple_in_Space_1",
    "DPS": "45459",
    "increase": "1.99%",
    "": ""
  },
  {
    "profile": "composite",
    "actor": "Reckless_Force_3",
    "DPS": "45455",
    "increase": "1.98%",
    "": ""
  },
  {
    "profile": "composite",
    "actor": "Condensed_Life_Force_1",
    "DPS": "45447",
    "increase": "1.96%",
    "": ""
  },
  {
    "profile": "composite",
    "actor": "Worldvein_Resonance_2_Allies_1",
    "DPS": "45389",
    "increase": "1.83%",
    "": ""
  },
  {
    "profile": "composite",
    "actor": "Conflict_1",
    "DPS": "45360",
    "increase": "1.77%",
    "": ""
  },
  {
    "profile": "composite",
    "actor": "Strife_1",
    "DPS": "45359",
    "increase": "1.76%",
    "": ""
  },
  {
    "profile": "composite",
    "actor": "The_Unbound_Force_2",
    "DPS": "45357",
    "increase": "1.76%",
    "": ""
  },
  {
    "profile": "composite",
    "actor": "Vision_of_Perfection_1",
    "DPS": "45354",
    "increase": "1.75%",
    "": ""
  },
  {
    "profile": "composite",
    "actor": "Lifeblood_1_Allies_1",
    "DPS": "45282",
    "increase": "1.59%",
    "": ""
  },
  {
    "profile": "composite",
    "actor": "The_Unbound_Force_1",
    "DPS": "45263",
    "increase": "1.55%",
    "": ""
  },
  {
    "profile": "composite",
    "actor": "Reckless_Force_2",
    "DPS": "45243",
    "increase": "1.50%",
    "": ""
  },
  {
    "profile": "composite",
    "actor": "Reckless_Force_1",
    "DPS": "45130",
    "increase": "1.25%",
    "": ""
  },
  {
    "profile": "composite",
    "actor": "Worldvein_Resonance_1_Allies_1",
    "DPS": "45070",
    "increase": "1.11%",
    "": ""
  },
  {
    "profile": "composite",
    "actor": "Strive_for_Perfection_3",
    "DPS": "44927",
    "increase": "0.79%",
    "": ""
  },
  {
    "profile": "composite",
    "actor": "Strive_for_Perfection_2",
    "DPS": "44707",
    "increase": "0.30%",
    "": ""
  },
  {
    "profile": "composite",
    "actor": "Strive_for_Perfection_1",
    "DPS": "44702",
    "increase": "0.29%",
    "": ""
  },
  {
    "profile": "composite",
    "actor": "Base",
    "DPS": "44573",
    "increase": "0.00%",
    "": ""
  },
  {
    "profile": "single_target",
    "actor": "Guardian_of_Azeroth_3",
    "DPS": "43707",
    "increase": "11.29%",
    "": ""
  },
  {
    "profile": "single_target",
    "actor": "Memory_of_Lucid_Dreams_3",
    "DPS": "43481",
    "increase": "10.71%",
    "": ""
  },
  {
    "profile": "single_target",
    "actor": "Concentrated_Flame_3",
    "DPS": "42850",
    "increase": "9.10%",
    "": ""
  },
  {
    "profile": "single_target",
    "actor": "Blood_of_the_Enemy_100_Uptime_3",
    "DPS": "42642",
    "increase": "8.58%",
    "": ""
  },
  {
    "profile": "single_target",
    "actor": "Memory_of_Lucid_Dreams_2",
    "DPS": "42328",
    "increase": "7.78%",
    "": ""
  },
  {
    "profile": "single_target",
    "actor": "Blood_of_the_Enemy_75_Uptime_3",
    "DPS": "42179",
    "increase": "7.40%",
    "": ""
  },
  {
    "profile": "single_target",
    "actor": "Blood_of_the_Enemy_100_Uptime_2",
    "DPS": "42024",
    "increase": "7.00%",
    "": ""
  },
  {
    "profile": "single_target",
    "actor": "Focused_Azerite_Beam_3",
    "DPS": "42009",
    "increase": "6.96%",
    "": ""
  },
  {
    "profile": "single_target",
    "actor": "Focused_Azerite_Beam_2",
    "DPS": "41926",
    "increase": "6.75%",
    "": ""
  },
  {
    "profile": "single_target",
    "actor": "Memory_of_Lucid_Dreams_1",
    "DPS": "41798",
    "increase": "6.43%",
    "": ""
  },
  {
    "profile": "single_target",
    "actor": "Concentrated_Flame_2",
    "DPS": "41756",
    "increase": "6.32%",
    "": ""
  },
  {
    "profile": "single_target",
    "actor": "Blood_of_the_Enemy_50_Uptime_3",
    "DPS": "41749",
    "increase": "6.30%",
    "": ""
  },
  {
    "profile": "single_target",
    "actor": "Blood_of_the_Enemy_75_Uptime_2",
    "DPS": "41638",
    "increase": "6.02%",
    "": ""
  },
  {
    "profile": "single_target",
    "actor": "Guardian_of_Azeroth_2",
    "DPS": "41632",
    "increase": "6.00%",
    "": ""
  },
  {
    "profile": "single_target",
    "actor": "Lifeblood_4_Allies_3",
    "DPS": "41502",
    "increase": "5.67%",
    "": ""
  },
  {
    "profile": "single_target",
    "actor": "Lifeblood_3_Allies_3",
    "DPS": "41448",
    "increase": "5.53%",
    "": ""
  },
  {
    "profile": "single_target",
    "actor": "Ancient_Flame_3",
    "DPS": "41339",
    "increase": "5.26%",
    "": ""
  },
  {
    "profile": "single_target",
    "actor": "Lifeblood_4_Allies_2",
    "DPS": "41325",
    "increase": "5.22%",
    "": ""
  },
  {
    "profile": "single_target",
    "actor": "Lucid_Dreams_3",
    "DPS": "41289",
    "increase": "5.13%",
    "": ""
  },
  {
    "profile": "single_target",
    "actor": "Lifeblood_2_Allies_3",
    "DPS": "41264",
    "increase": "5.07%",
    "": ""
  },
  {
    "profile": "single_target",
    "actor": "Blood_of_the_Enemy_50_Uptime_2",
    "DPS": "41244",
    "increase": "5.01%",
    "": ""
  },
  {
    "profile": "single_target",
    "actor": "Focused_Energy_3",
    "DPS": "41236",
    "increase": "5.00%",
    "": ""
  },
  {
    "profile": "single_target",
    "actor": "Focused_Energy_2",
    "DPS": "41209",
    "increase": "4.93%",
    "": ""
  },
  {
    "profile": "single_target",
    "actor": "Lifeblood_3_Allies_2",
    "DPS": "41113",
    "increase": "4.68%",
    "": ""
  },
  {
    "profile": "single_target",
    "actor": "Worldvein_Resonance_4_Allies_3",
    "DPS": "41077",
    "increase": "4.59%",
    "": ""
  },
  {
    "profile": "single_target",
    "actor": "Worldvein_Resonance_3_Allies_3",
    "DPS": "41040",
    "increase": "4.50%",
    "": ""
  },
  {
    "profile": "single_target",
    "actor": "Focused_Azerite_Beam_1",
    "DPS": "41031",
    "increase": "4.47%",
    "": ""
  },
  {
    "profile": "single_target",
    "actor": "Blood_of_the_Enemy_100_Uptime_1",
    "DPS": "41021",
    "increase": "4.45%",
    "": ""
  },
  {
    "profile": "single_target",
    "actor": "Condensed_Life_Force_3",
    "DPS": "41015",
    "increase": "4.43%",
    "": ""
  },
  {
    "profile": "single_target",
    "actor": "Guardian_of_Azeroth_1",
    "DPS": "40981",
    "increase": "4.35%",
    "": ""
  },
  {
    "profile": "single_target",
    "actor": "Conflict_3",
    "DPS": "40968",
    "increase": "4.31%",
    "": ""
  },
  {
    "profile": "single_target",
    "actor": "Strife_3",
    "DPS": "40966",
    "increase": "4.31%",
    "": ""
  },
  {
    "profile": "single_target",
    "actor": "Worldvein_Resonance_4_Allies_2",
    "DPS": "40960",
    "increase": "4.29%",
    "": ""
  },
  {
    "profile": "single_target",
    "actor": "Worldvein_Resonance_2_Allies_3",
    "DPS": "40940",
    "increase": "4.24%",
    "": ""
  },
  {
    "profile": "single_target",
    "actor": "Blood_Soaked_3",
    "DPS": "40901",
    "increase": "4.14%",
    "": ""
  },
  {
    "profile": "single_target",
    "actor": "Worldvein_Resonance_3_Allies_2",
    "DPS": "40821",
    "increase": "3.94%",
    "": ""
  },
  {
    "profile": "single_target",
    "actor": "Lifeblood_1_Allies_3",
    "DPS": "40805",
    "increase": "3.90%",
    "": ""
  },
  {
    "profile": "single_target",
    "actor": "Blood_Soaked_2",
    "DPS": "40785",
    "increase": "3.85%",
    "": ""
  },
  {
    "profile": "single_target",
    "actor": "Concentrated_Flame_1",
    "DPS": "40773",
    "increase": "3.82%",
    "": ""
  },
  {
    "profile": "single_target",
    "actor": "Lifeblood_4_Allies_1",
    "DPS": "40769",
    "increase": "3.80%",
    "": ""
  },
  {
    "profile": "single_target",
    "actor": "The_Unbound_Force_3",
    "DPS": "40766",
    "increase": "3.80%",
    "": ""
  },
  {
    "profile": "single_target",
    "actor": "Purifying_Blast_3",
    "DPS": "40726",
    "increase": "3.70%",
    "": ""
  },
  {
    "profile": "single_target",
    "actor": "Blood_of_the_Enemy_75_Uptime_1",
    "DPS": "40716",
    "increase": "3.67%",
    "": ""
  },
  {
    "profile": "single_target",
    "actor": "Lifeblood_2_Allies_2",
    "DPS": "40659",
    "increase": "3.53%",
    "": ""
  },
  {
    "profile": "single_target",
    "actor": "Worldvein_Resonance_1_Allies_3",
    "DPS": "40568",
    "increase": "3.30%",
    "": ""
  },
  {
    "profile": "single_target",
    "actor": "Vision_of_Perfection_3",
    "DPS": "40568",
    "increase": "3.29%",
    "": ""
  },
  {
    "profile": "single_target",
    "actor": "Focused_Energy_1",
    "DPS": "40567",
    "increase": "3.29%",
    "": ""
  },
  {
    "profile": "single_target",
    "actor": "Purifying_Blast_2",
    "DPS": "40532",
    "increase": "3.20%",
    "": ""
  },
  {
    "profile": "single_target",
    "actor": "Lifeblood_3_Allies_1",
    "DPS": "40529",
    "increase": "3.19%",
    "": ""
  },
  {
    "profile": "single_target",
    "actor": "Purifying_Blast_1",
    "DPS": "40526",
    "increase": "3.19%",
    "": ""
  },
  {
    "profile": "single_target",
    "actor": "Worldvein_Resonance_2_Allies_2",
    "DPS": "40493",
    "increase": "3.10%",
    "": ""
  },
  {
    "profile": "single_target",
    "actor": "Worldvein_Resonance_4_Allies_1",
    "DPS": "40446",
    "increase": "2.98%",
    "": ""
  },
  {
    "profile": "single_target",
    "actor": "Blood_of_the_Enemy_50_Uptime_1",
    "DPS": "40399",
    "increase": "2.86%",
    "": ""
  },
  {
    "profile": "single_target",
    "actor": "Strife_2",
    "DPS": "40394",
    "increase": "2.85%",
    "": ""
  },
  {
    "profile": "single_target",
    "actor": "Conflict_2",
    "DPS": "40387",
    "increase": "2.83%",
    "": ""
  },
  {
    "profile": "single_target",
    "actor": "Condensed_Life_Force_2",
    "DPS": "40371",
    "increase": "2.79%",
    "": ""
  },
  {
    "profile": "single_target",
    "actor": "Ancient_Flame_2",
    "DPS": "40334",
    "increase": "2.70%",
    "": ""
  },
  {
    "profile": "single_target",
    "actor": "Vision_of_Perfection_2",
    "DPS": "40272",
    "increase": "2.54%",
    "": ""
  },
  {
    "profile": "single_target",
    "actor": "Worldvein_Resonance_3_Allies_1",
    "DPS": "40232",
    "increase": "2.44%",
    "": ""
  },
  {
    "profile": "single_target",
    "actor": "Lucid_Dreams_2",
    "DPS": "40215",
    "increase": "2.40%",
    "": ""
  },
  {
    "profile": "single_target",
    "actor": "Purification_Protocol_3",
    "DPS": "40205",
    "increase": "2.37%",
    "": ""
  },
  {
    "profile": "single_target",
    "actor": "Lucid_Dreams_1",
    "DPS": "40202",
    "increase": "2.36%",
    "": ""
  },
  {
    "profile": "single_target",
    "actor": "Lifeblood_2_Allies_1",
    "DPS": "40200",
    "increase": "2.36%",
    "": ""
  },
  {
    "profile": "single_target",
    "actor": "Lifeblood_1_Allies_2",
    "DPS": "40191",
    "increase": "2.33%",
    "": ""
  },
  {
    "profile": "single_target",
    "actor": "Condensed_Life_Force_1",
    "DPS": "40158",
    "increase": "2.25%",
    "": ""
  },
  {
    "profile": "single_target",
    "actor": "Worldvein_Resonance_1_Allies_2",
    "DPS": "40141",
    "increase": "2.21%",
    "": ""
  },
  {
    "profile": "single_target",
    "actor": "Ancient_Flame_1",
    "DPS": "40123",
    "increase": "2.16%",
    "": ""
  },
  {
    "profile": "single_target",
    "actor": "Ripple_in_Space_2",
    "DPS": "40073",
    "increase": "2.03%",
    "": ""
  },
  {
    "profile": "single_target",
    "actor": "Ripple_in_Space_3",
    "DPS": "40061",
    "increase": "2.00%",
    "": ""
  },
  {
    "profile": "single_target",
    "actor": "The_Unbound_Force_2",
    "DPS": "40059",
    "increase": "2.00%",
    "": ""
  },
  {
    "profile": "single_target",
    "actor": "Blood_Soaked_1",
    "DPS": "40035",
    "increase": "1.94%",
    "": ""
  },
  {
    "profile": "single_target",
    "actor": "Purification_Protocol_2",
    "DPS": "40015",
    "increase": "1.89%",
    "": ""
  },
  {
    "profile": "single_target",
    "actor": "Purification_Protocol_1",
    "DPS": "40015",
    "increase": "1.88%",
    "": ""
  },
  {
    "profile": "single_target",
    "actor": "Vision_of_Perfection_1",
    "DPS": "39992",
    "increase": "1.83%",
    "": ""
  },
  {
    "profile": "single_target",
    "actor": "Reckless_Force_3",
    "DPS": "39989",
    "increase": "1.82%",
    "": ""
  },
  {
    "profile": "single_target",
    "actor": "Strife_1",
    "DPS": "39967",
    "increase": "1.76%",
    "": ""
  },
  {
    "profile": "single_target",
    "actor": "Worldvein_Resonance_2_Allies_1",
    "DPS": "39961",
    "increase": "1.75%",
    "": ""
  },
  {
    "profile": "single_target",
    "actor": "Conflict_1",
    "DPS": "39959",
    "increase": "1.74%",
    "": ""
  },
  {
    "profile": "single_target",
    "actor": "Ripple_in_Space_1",
    "DPS": "39910",
    "increase": "1.62%",
    "": ""
  },
  {
    "profile": "single_target",
    "actor": "Lifeblood_1_Allies_1",
    "DPS": "39898",
    "increase": "1.59%",
    "": ""
  },
  {
    "profile": "single_target",
    "actor": "The_Unbound_Force_1",
    "DPS": "39891",
    "increase": "1.57%",
    "": ""
  },
  {
    "profile": "single_target",
    "actor": "Reckless_Force_2",
    "DPS": "39811",
    "increase": "1.37%",
    "": ""
  },
  {
    "profile": "single_target",
    "actor": "Reckless_Force_1",
    "DPS": "39728",
    "increase": "1.16%",
    "": ""
  },
  {
    "profile": "single_target",
    "actor": "Worldvein_Resonance_1_Allies_1",
    "DPS": "39682",
    "increase": "1.04%",
    "": ""
  },
  {
    "profile": "single_target",
    "actor": "Strive_for_Perfection_3",
    "DPS": "39579",
    "increase": "0.78%",
    "": ""
  },
  {
    "profile": "single_target",
    "actor": "Strive_for_Perfection_2",
    "DPS": "39387",
    "increase": "0.29%",
    "": ""
  },
  {
    "profile": "single_target",
    "actor": "Strive_for_Perfection_1",
    "DPS": "39376",
    "increase": "0.26%",
    "": ""
  },
  {
    "profile": "single_target",
    "actor": "Base",
    "DPS": "39274",
    "increase": "0.00%",
    "": ""
  }
]